Workbook

Sheet Summary
A1: PA-07 campaign finance: where the money is
A2: Pennsylvania's 7th congressional district. Bob Brooks (D) and Ryan Mackenzie (R). General election 2026-11-03. Source: FEC.
A4: DATA VINTAGE, READ THIS FIRST
A5: Candidate committee totals current through | B5: 2026-10-14 | C5: Latest periodic FEC report on file for the nominees
A6: Outside spending | B6: continuous | C6: Reported as it happens; fresher than the candidate totals
A7: Data retrieved | B7: 2026-10-24T13:15:11Z | C7: Next candidate report: October Quarterly, due 2026-10-15
A9: MONEY AT A GLANCE
B10: Bob Brooks (D) | C10: Ryan Mackenzie (R) | D10: R minus D
A11: Total receipts | B11: ='Money Sources'!B18 | C11: ='Money Sources'!C18 | D11: =IF(AND(ISNUMBER(C11),ISNUMBER(B11)),C11-B11,"")
A12: less: transfers from another committee | B12: ='Money Sources'!B19 | C12: ='Money Sources'!C19 | D12: =IF(AND(ISNUMBER(C12),ISNUMBER(B12)),C12-B12,"")
A13: Receipts excluding transfers | B13: ='Money Sources'!B20 | C13: ='Money Sources'!C20 | D13: =IF(AND(ISNUMBER(C13),ISNUMBER(B13)),C13-B13,"")
A14: Disbursements | B14: ='Money Sources'!B31 | C14: ='Money Sources'!C31 | D14: =IF(AND(ISNUMBER(C14),ISNUMBER(B14)),C14-B14,"")
A15: Cash on hand | B15: ='Money Sources'!B32 | C15: ='Money Sources'!C32 | D15: =IF(AND(ISNUMBER(C15),ISNUMBER(B15)),C15-B15,"")
A16: Debts owed | B16: ='Money Sources'!B33 | C16: ='Money Sources'!C33 | D16: =IF(AND(ISNUMBER(C16),ISNUMBER(B16)),C16-B16,"")
A17: Burn rate (disbursed / raised) | B17: ='Money Sources'!B34 | C17: ='Money Sources'!C34 | D17: =IF(AND(ISNUMBER(C17),ISNUMBER(B17)),C17-B17,"")
A19: OUTSIDE SPENDING
B20: Amount | C20: Share of all outside spending | D20: Committees
A21: All independent expenditures about the two nominees | B21: ='Outside Money'!D44 | D21: ='Outside Money'!D52
A22: Bob Brooks, supports | B22: ='Outside Money'!C48 | C22: =IFERROR(B22/$B$21,"") | D22: ='Outside Money'!D48
A23: Bob Brooks, opposes | B23: ='Outside Money'!C49 | C23: =IFERROR(B23/$B$21,"") | D23: ='Outside Money'!D49
A24: Ryan Mackenzie, supports | B24: ='Outside Money'!C50 | C24: =IFERROR(B24/$B$21,"") | D24: ='Outside Money'!D50
A25: Ryan Mackenzie, opposes | B25: ='Outside Money'!C51 | C25: =IFERROR(B25/$B$21,"") | D25: ='Outside Money'!D51
A27: THE LAST FOUR ELECTIONS
B28: 2018 | C28: 2020 | D28: 2022 | E28: 2024
A29: Democratic share of candidate receipts | B29: ='Money vs Results'!D6 | C29: ='Money vs Results'!D7 | D29: ='Money vs Results'!D8 | E29: ='Money vs Results'!D9
A30: Democratic share of all aligned money | B30: ='Money vs Results'!G6 | C30: ='Money vs Results'!G7 | D30: ='Money vs Results'!G8 | E30: ='Money vs Results'!G9
A31: Democratic two-party vote share | B31: ='Money vs Results'!H6 | C31: ='Money vs Results'!H7 | D31: ='Money vs Results'!H8 | E31: ='Money vs Results'!H9
A32: Democratic result | B32: won | C32: won | D32: won | E32: lost
A34: Correlation, candidate receipts share vs vote share (Model A) | B34: ='Money vs Results'!B14 | C34: ='Money vs Results'!B20
A35: Correlation, all aligned money share vs vote share (Model B) | B35: ='Money vs Results'!C14 | C35: ='Money vs Results'!C20
A37: TWO FACTS THE MONEY MUST BE READ WITH
A38: 1. The two halves are not as of the same date. Candidate totals stop at the latest periodic report and are usually months stale. Outside spending reports continuously. Do not compare a candidate figure and an outside-money figure as though they were measured on the same day.
A39: 2. Much of this money was not spent on the November race. The largest outside-spending committees were active in May 2026, inside the contested Democratic primary, and a large share of the Republican nominee's receipts is a transfer from a wound-down joint committee rather than new donor money. The naive reading of the headline totals is wrong in a way that changes the conclusion.
A41: Green figures link to other sheets. Navy figures are computed here. Nothing on this sheet is typed in by hand.

Sheet Master Data
A1: Master data: every figure in this workbook, one row per fact
A2: Values, not formulas. Filter on Dataset to isolate one table. Amounts in US dollars; Count is items, filings, gifts or votes depending on the dataset; Date is the coverage or election date.
A4: Dataset | B4: Cycle | C4: Candidate | D4: Party | E4: Stance | F4: Category | G4: Item | H4: Description | I4: City | J4: State | K4: Amount | L4: Count | M4: Date
A5: candidate_totals | B5: 2026 | C5: Bob Brooks | D5: DEM | G5: Receipts | K5: 5347353.4 | M5: 2026-10-14
A6: candidate_totals | B6: 2026 | C6: Bob Brooks | D6: DEM | G6: Disbursements | K6: 4605774.9 | M6: 2026-10-14
A7: candidate_totals | B7: 2026 | C7: Bob Brooks | D7: DEM | G7: Cash on hand | K7: 741578.51 | M7: 2026-10-14
A8: candidate_totals | B8: 2026 | C8: Bob Brooks | D8: DEM | G8: Debts | K8: 15000 | M8: 2026-10-14
A9: candidate_totals | B9: 2026 | C9: Bob Brooks | D9: DEM | G9: Individual contributions, total | K9: 4181508.3 | M9: 2026-10-14
A10: candidate_totals | B10: 2026 | C10: Bob Brooks | D10: DEM | G10: Individual contributions, itemized (over $200) | K10: 3013669.4 | M10: 2026-10-14
A11: candidate_totals | B11: 2026 | C11: Bob Brooks | D11: DEM | G11: Individual contributions, unitemized ($200 or less) | K11: 1167838.9 | M11: 2026-10-14
A12: candidate_totals | B12: 2026 | C12: Bob Brooks | D12: DEM | G12: PAC contributions | K12: 634750.03 | M12: 2026-10-14
A13: candidate_totals | B13: 2026 | C13: Bob Brooks | D13: DEM | G13: Party committee contributions | K13: 6090.07 | M13: 2026-10-14
A14: candidate_totals | B14: 2026 | C14: Bob Brooks | D14: DEM | G14: Transfers from other authorized committee | K14: 508989.33 | M14: 2026-10-14
A15: candidate_totals | B15: 2026 | C15: Bob Brooks | D15: DEM | G15: Candidate self-funding | K15: 3500 | M15: 2026-10-14
A16: candidate_totals | B16: 2026 | C16: Ryan Mackenzie | D16: REP | G16: Receipts | K16: 5296663.9 | M16: 2026-10-14
... A26: candidate_totals | B26: 2026 | C26: Ryan Mackenzie | D26: REP | G26: Candidate self-funding | K26: 0 | M26: 2026-10-14
A27: outside_by_committee | B27: 2026 | C27: Bob Brooks | E27: Supports | G27: STRONGER TOGETHER PA | K27: 1781524 | L27: 21
A28: outside_by_committee | B28: 2026 | C28: Ryan Mackenzie | E28: Opposes | G28: HMP | K28: 556259.93 | L28: 11
A29: outside_by_committee | B29: 2026 | C29: Bob Brooks | E29: Opposes | G29: LEAD LEFT PAC | K29: 312371.76 | L29: 7
A30: outside_by_committee | B30: 2026 | C30: Bob Brooks | E30: Supports | G30: JOBS AND DEMOCRACY PAC | K30: 249750 | L30: 1
A31: outside_by_committee | B31: 2026 | C31: Bob Brooks | E31: Supports | G31: CONGRESSIONAL PROGRESSIVE CAUCUS PAC | K31: 140300 | L31: 2
A32: outside_by_committee | B32: 2026 | C32: Bob Brooks | E32: Supports | G32: MEDICARE FOR ALL | K32: 99625 | L32: 2
A33: outside_by_committee | B33: 2026 | C33: Bob Brooks | E33: Supports | G33: DLP PAC | K33: 88321.5 | L33: 4
A34: outside_by_committee | B34: 2026 | C34: Bob Brooks | E34: Supports | G34: WORKING FAMILIES PARTY PAC | K34: 41020.59 | L34: 3
A35: outside_by_committee | B35: 2026 | C35: Bob Brooks | E35: Supports | G35: RURAL FREEDOM NETWORK | K35: 30756.92 | L35: 5
A36: outside_by_committee | B36: 2026 | C36: Bob Brooks | E36: Supports | G36: MAKE THE ROAD ACTION POLITICAL COMMITTEE | K36: 30559.95 | L36: 9
A37: outside_by_committee | B37: 2026 | C37: Bob Brooks | E37: Supports | G37: HMP | K37: 30281.38 | L37: 4
A38: outside_by_committee | B38: 2026 | C38: Ryan Mackenzie | E38: Opposes | G38: IN UNION USA | K38: 26382.22 | L38: 1
... A64: outside_by_committee | B64: 2026 | C64: Ryan Mackenzie | E64: Supports | G64: PENNSYLVANIA PRO-LIFE FEDERATION PAC | K64: 22.94 | L64: 1
A65: outside_itemized | B65: 2026 | C65: Bob Brooks | E65: Supports | F65: Television and media buys | G65: STRONGER TOGETHER PA | H65: AD BUY | I65: PHILADELPHIA | J65: PA | K65: 306418 | M65: 2026-05-05
A66: outside_itemized | B66: 2026 | C66: Bob Brooks | E66: Supports | F66: Television and media buys | G66: STRONGER TOGETHER PA | H66: AD BUY | I66: PHILADELPHIA | J66: PA | K66: 272247 | M66: 2026-04-01
A67: outside_itemized | B67: 2026 | C67: Bob Brooks | E67: Supports | F67: Digital advertising | G67: JOBS AND DEMOCRACY PAC | H67: DIGITAL BUY | I67: SANTA BARBARA | J67: CA | K67: 249750 | M67: 2026-05-15
A68: outside_itemized | B68: 2026 | C68: Bob Brooks | E68: Supports | F68: Television and media buys | G68: STRONGER TOGETHER PA | H68: AD BUY | I68: PHILADELPHIA | J68: PA | K68: 175000 | M68: 2026-05-13
A69: outside_itemized | B69: 2026 | C69: Bob Brooks | E69: Supports | F69: Television and media buys | G69: STRONGER TOGETHER PA | H69: AD BUY | I69: PHILADELPHIA | J69: PA | K69: 154509 | M69: 2026-04-23
A70: outside_itemized | B70: 2026 | C70: Bob Brooks | E70: Supports | F70: Television and media buys | G70: STRONGER TOGETHER PA | H70: AD BUY | I70: PHILADELPHIA | J70: PA | K70: 150000 | M70: 2026-05-15
A71: outside_itemized | B71: 2026 | C71: Ryan Mackenzie | E71: Opposes | F71: Digital advertising | G71: HMP | H71: DIGITAL ADVERTISING | I71: WASHINGTON | J71: DC | K71: 130875 | M71: 2026-09-25
A72: outside_itemized | B72: 2026 | C72: Ryan Mackenzie | E72: Opposes | F72: Digital advertising | G72: HMP | H72: DIGITAL ADVERTISING | I72: WASHINGTON | J72: DC | K72: 130875 | M72: 2026-09-23
A73: outside_itemized | B73: 2026 | C73: Bob Brooks | E73: Supports | F73: Digital advertising | G73: CONGRESSIONAL PROGRESSIVE CAUCUS PAC | H73: DIGITAL AD BUY - ESTIMATE | I73: BERKELEY | J73: CA | K73: 128000 | M73: 2026-04-24
A74: outside_itemized | B74: 2026 | C74: Ryan Mackenzie | E74: Opposes | F74: Digital advertising | G74: HMP | H74: DIGITAL ADVERTISING | I74: WASHINGTON | J74: DC | K74: 117732.94 | M74: 2026-09-14
A75: outside_itemized | B75: 2026 | C75: Bob Brooks | E75: Supports | F75: Television and media buys | G75: STRONGER TOGETHER PA | H75: AD BUY | I75: PHILADELPHIA | J75: PA | K75: 110000 | M75: 2026-05-15
A76: outside_itemized | B76: 2026 | C76: Bob Brooks | E76: Opposes | F76: Television and media buys | G76: LEAD LEFT PAC | H76: MEDIA PLACEMENT / MEDIA PRODUCTION | I76: RICHMOND | J76: VA | K76: 106756.66 | M76: 2026-05-05
... A202: outside_itemized | B202: 2026 | C202: Bob Brooks | E202: Supports | F202: Texting and phone calls | G202: GIVEGREEN UNITED ACTION | H202: TEXT MESSAGING | I202: BETHESDA | J202: MD | K202: 4.54 | M202: 2026-06-25
A203: spending_by_category | B203: 2026 | C203: Bob Brooks | D203: DEM | F203: Television advertising | K203: 521229 | L203: 9 | M203: 2026-10-14
A204: spending_by_category | B204: 2026 | C204: Bob Brooks | D204: DEM | F204: Digital advertising | K204: 258938.16 | L204: 19 | M204: 2026-10-14
A205: spending_by_category | B205: 2026 | C205: Bob Brooks | D205: DEM | F205: Staff and payroll | K205: 204066.98 | L205: 61 | M205: 2026-10-14
A206: spending_by_category | B206: 2026 | C206: Bob Brooks | D206: DEM | F206: Fundraising | K206: 105581.67 | L206: 169 | M206: 2026-10-14
A207: spending_by_category | B207: 2026 | C207: Bob Brooks | D207: DEM | F207: Office and administrative | K207: 94451.94 | L207: 48 | M207: 2026-10-14
A208: spending_by_category | B208: 2026 | C208: Bob Brooks | D208: DEM | F208: Field, phones and texting | K208: 49977.25 | L208: 16 | M208: 2026-10-14
A209: spending_by_category | B209: 2026 | C209: Bob Brooks | D209: DEM | F209: Polling and research | K209: 41005 | L209: 8 | M209: 2026-10-14
A210: spending_by_category | B210: 2026 | C210: Bob Brooks | D210: DEM | F210: Media production | K210: 34156.56 | L210: 5 | M210: 2026-10-14
A211: spending_by_category | B211: 2026 | C211: Bob Brooks | D211: DEM | F211: Mail and printing | K211: 22167.78 | L211: 15 | M211: 2026-10-14
A212: spending_by_category | B212: 2026 | C212: Bob Brooks | D212: DEM | F212: Refunds | K212: 10375 | L212: 12 | M212: 2026-10-14
A213: spending_by_category | B213: 2026 | C213: Bob Brooks | D213: DEM | F213: Consulting | K213: 10000 | L213: 1 | M213: 2026-10-14
A214: spending_by_category | B214: 2026 | C214: Bob Brooks | D214: DEM | F214: Travel | K214: 6186.67 | L214: 20 | M214: 2026-10-14
... A218: spending_by_category | B218: 2026 | C218: Bob Brooks | D218: DEM | F218: Signs and merchandise | K218: 750 | L218: 1 | M218: 2026-10-14
A219: spending_top_payees | B219: 2026 | C219: Bob Brooks | D219: DEM | F219: Television advertising | G219: LC MEDIA LLC | I219: HUNTINGDON VALLEY | J219: PA | K219: 543229 | L219: 11 | M219: 2026-10-14
A220: spending_top_payees | B220: 2026 | C220: Bob Brooks | D220: DEM | F220: Digital advertising | G220: ASCEND DIGITAL | I220: WASHINGTON | J220: DC | K220: 203646.79 | L220: 7 | M220: 2026-10-14
A221: spending_top_payees | B221: 2026 | C221: Bob Brooks | D221: DEM | F221: Staff and payroll | G221: KAUFMAN, JENNA | I221: BETHLEHEM | J221: PA | K221: 75187.4 | L221: 16 | M221: 2026-10-14
A222: spending_top_payees | B222: 2026 | C222: Bob Brooks | D222: DEM | F222: Staff and payroll | G222: WERNER, JACK | I222: EASTON | J222: PA | K222: 58673.23 | L222: 17 | M222: 2026-10-14
A223: spending_top_payees | B223: 2026 | C223: Bob Brooks | D223: DEM | F223: Staff and payroll | G223: PAYCHEX | I223: ROCHESTER | J223: NY | K223: 54920.71 | L223: 35 | M223: 2026-10-14
A224: spending_top_payees | B224: 2026 | C224: Bob Brooks | D224: DEM | F224: Fundraising | G224: ACTBLUE TECHNICAL SERVICES | I224: WEST SOMERVILLE | J224: MA | K224: 54605.66 | L224: 76 | M224: 2026-10-14
A225: spending_top_payees | B225: 2026 | C225: Bob Brooks | D225: DEM | F225: Polling and research | G225: ARC INITIATIVES | I225: WASHINGTON | J225: DC | K225: 35000 | L225: 7 | M225: 2026-10-14
A226: spending_top_payees | B226: 2026 | C226: Bob Brooks | D226: DEM | F226: Digital advertising | G226: TRUE BLUE DIGITAL | I226: CHICAGO | J226: IL | K226: 34817.13 | L226: 8 | M226: 2026-10-14
A227: spending_top_payees | B227: 2026 | C227: Bob Brooks | D227: DEM | F227: Office and administrative | G227: NGP VAN | I227: AUSTIN | J227: TX | K227: 31749.04 | L227: 5 | M227: 2026-10-14
A228: spending_top_payees | B228: 2026 | C228: Bob Brooks | D228: DEM | F228: Office and administrative | G228: CFO COMPLIANCE | I228: PROVIDENCE | J228: RI | K228: 26182.97 | L228: 9 | M228: 2026-10-14
A229: spending_top_payees | B229: 2026 | C229: Bob Brooks | D229: DEM | F229: Staff and payroll | G229: WRIGLEY, JOHN | I229: ALLENTOWN | J229: PA | K229: 22312 | L229: 8 | M229: 2026-10-14
A230: spending_top_payees | B230: 2026 | C230: Bob Brooks | D230: DEM | F230: Fundraising | G230: GRASSROOTS ANALYTICS | I230: WASHINGTON | J230: DC | K230: 17832.07 | L230: 12 | M230: 2026-10-14
... A233: spending_top_payees | B233: 2026 | C233: Bob Brooks | D233: DEM | F233: Digital advertising | G233: SOUTH STREET DIGITAL | I233: PHILADELPHIA | J233: PA | K233: 14003.2 | L233: 3 | M233: 2026-10-14
A234: spending_by_payee_state | B234: 2026 | C234: Bob Brooks | D234: DEM | J234: PA | K234: 798926.02 | L234: 101 | M234: 2026-10-14
A235: spending_by_payee_state | B235: 2026 | C235: Bob Brooks | D235: DEM | J235: DC | K235: 274955.33 | L235: 64 | M235: 2026-10-14
A236: spending_by_payee_state | B236: 2026 | C236: Bob Brooks | D236: DEM | J236: NY | K236: 69953.94 | L236: 44 | M236: 2026-10-14
A237: spending_by_payee_state | B237: 2026 | C237: Bob Brooks | D237: DEM | J237: MA | K237: 57354.54 | L237: 82 | M237: 2026-10-14
A238: spending_by_payee_state | B238: 2026 | C238: Bob Brooks | D238: DEM | J238: CA | K238: 39080.7 | L238: 35 | M238: 2026-10-14
A239: spending_by_payee_state | B239: 2026 | C239: Bob Brooks | D239: DEM | J239: IL | K239: 35315.53 | L239: 9 | M239: 2026-10-14
A240: spending_by_payee_state | B240: 2026 | C240: Bob Brooks | D240: DEM | J240: TX | K240: 32737.44 | L240: 7 | M240: 2026-10-14
A241: spending_by_payee_state | B241: 2026 | C241: Bob Brooks | D241: DEM | J241: RI | K241: 26182.97 | L241: 9 | M241: 2026-10-14
A242: spending_by_payee_state | B242: 2026 | C242: Bob Brooks | D242: DEM | J242: MD | K242: 20343.22 | L242: 16 | M242: 2026-10-14
A243: spending_by_payee_state | B243: 2026 | C243: Bob Brooks | D243: DEM | J243: DE | K243: 7398.65 | L243: 27 | M243: 2026-10-14
A244: spending_by_payee_state | B244: 2026 | C244: Bob Brooks | D244: DEM | J244: WA | K244: 2217.46 | L244: 1 | M244: 2026-10-14
A245: spending_by_payee_state | B245: 2026 | C245: Bob Brooks | D245: DEM | J245: VA | K245: 1000 | L245: 1 | M245: 2026-10-14
... A297: contributions_by_state | B297: 2026 | C297: Bob Brooks | D297: DEM | J297: TN | K297: 250 | L297: 1 | M297: 2026-10-14
A298: contributions_by_size | B298: 2026 | C298: Bob Brooks | D298: DEM | F298: $200 or less | K298: 1213578.7 | M298: 2026-10-14
A299: contributions_by_size | B299: 2026 | C299: Bob Brooks | D299: DEM | F299: $200.01 to $499.99 | K299: 122396.32 | L299: 453 | M299: 2026-10-14
A300: contributions_by_size | B300: 2026 | C300: Bob Brooks | D300: DEM | F300: $500 to $999.99 | K300: 151953.87 | L300: 292 | M300: 2026-10-14
A301: contributions_by_size | B301: 2026 | C301: Bob Brooks | D301: DEM | F301: $1,000 to $1,999.99 | K301: 243422.46 | L301: 224 | M301: 2026-10-14
A302: contributions_by_size | B302: 2026 | C302: Bob Brooks | D302: DEM | F302: $2,000 and over | K302: 798593.73 | L302: 246 | M302: 2026-10-14
A303: contributions_in_district | B303: 2026 | C303: Bob Brooks | D303: DEM | F303: Zip codes 180xx, 181xx, 182xx, 183xx | G303: In district (approximate) | K303: 92671.33 | M303: 2026-10-14
A304: contributions_in_district | B304: 2026 | C304: Bob Brooks | D304: DEM | G304: All itemized, by zip | K304: 1362106.2 | L304: 679 | M304: 2026-10-14
A305: contributions_top_zips | B305: 2026 | C305: Bob Brooks | D305: DEM | G305: 18064 | K305: 31450 | L305: 38 | M305: 2026-10-14
A306: contributions_top_zips | B306: 2026 | C306: Bob Brooks | D306: DEM | G306: 19103 | K306: 25050 | L306: 15 | M306: 2026-10-14
A307: contributions_top_zips | B307: 2026 | C307: Bob Brooks | D307: DEM | G307: 10011 | K307: 24000 | L307: 9 | M307: 2026-10-14
A308: contributions_top_zips | B308: 2026 | C308: Bob Brooks | D308: DEM | G308: 10024 | K308: 22813.08 | L308: 27 | M308: 2026-10-14
A309: contributions_top_zips | B309: 2026 | C309: Bob Brooks | D309: DEM | G309: 06830 | K309: 21500 | L309: 8 | M309: 2026-10-14
A310: contributions_top_zips | B310: 2026 | C310: Bob Brooks | D310: DEM | G310: 11238 | K310: 20500 | L310: 9 | M310: 2026-10-14
A311: contributions_top_zips | B311: 2026 | C311: Bob Brooks | D311: DEM | G311: 94027 | K311: 18675 | L311: 8 | M311: 2026-10-14
A312: contributions_top_zips | B312: 2026 | C312: Bob Brooks | D312: DEM | G312: 10012 | K312: 17750 | L312: 6 | M312: 2026-10-14
A313: contributions_top_zips | B313: 2026 | C313: Bob Brooks | D313: DEM | G313: 94301 | K313: 17750 | L313: 6 | M313: 2026-10-14
A314: contributions_top_zips | B314: 2026 | C314: Bob Brooks | D314: DEM | G314: 10075 | K314: 17500 | L314: 5 | M314: 2026-10-14
A315: contributions_by_occupation | B315: 2026 | C315: Bob Brooks | D315: DEM | G315: NOT EMPLOYED | K315: 453408.96 | L315: 950 | M315: 2026-10-14
... A326: contributions_by_occupation | B326: 2026 | C326: Bob Brooks | D326: DEM | G326: FINANCE | K326: 14472.22 | L326: 6 | M326: 2026-10-14
...

Sheet Charts
A1: Where the money is: charts
A2: Every series links to the data sheets. Chart source data sits in columns R onward. | R2: CHART 1: receipts, spending and cash
R3: Metric | S3: Bob Brooks (D) | T3: Ryan Mackenzie (R)
R4: Receipts | S4: ='Money Sources'!B30 | T4: ='Money Sources'!C30
R5: Disbursements | S5: ='Money Sources'!B31 | T5: ='Money Sources'!C31
R6: Cash on hand | S6: ='Money Sources'!B32 | T6: ='Money Sources'!C32
R8: CHART 2: receipts by source
R9: Candidate | S9: Individual, itemized (over $200) | T9: Individual, unitemized ($200 or less) | U9: PAC contributions | V9: Party committee | W9: Transfers from another authorized committee | X9: Candidate self-funding | Y9: Other / unclassified
R10: Bob Brooks (D) | S10: ='Money Sources'!B6 | T10: ='Money Sources'!B7 | U10: ='Money Sources'!B8 | V10: ='Money Sources'!B9 | W10: ='Money Sources'!B10 | X10: ='Money Sources'!B11 | Y10: ='Money Sources'!B12
R11: Ryan Mackenzie (R) | S11: ='Money Sources'!C6 | T11: ='Money Sources'!C7 | U11: ='Money Sources'!C8 | V11: ='Money Sources'!C9 | W11: ='Money Sources'!C10 | X11: ='Money Sources'!C11 | Y11: ='Money Sources'!C12
R13: CHART 3: headline receipts against receipts excluding transfers
R14: Measure | S14: Bob Brooks (D) | T14: Ryan Mackenzie (R)
R15: Receipts as reported | S15: ='Money Sources'!B18 | T15: ='Money Sources'!C18
R16: Excluding committee transfers | S16: ='Money Sources'!B20 | T16: ='Money Sources'!C20
R18: CHART 4: ten largest outside spenders
R19: Committee | S19: Independent expenditure
R20: Stronger Together PA (supports Brooks) | S20: ='Outside Money'!D6
R21: Hmp (opposes Mackenzie) | S21: ='Outside Money'!D7
R22: Lead Left PAC (opposes Brooks) | S22: ='Outside Money'!D8
R23: Jobs and Democracy PAC (supports Brooks) | S23: ='Outside Money'!D9
R24: Congressional Progressive Caucus PAC (supports Brooks) | S24: ='Outside Money'!D10
R25: Medicare for All (supports Brooks) | S25: ='Outside Money'!D11
R26: DLP PAC (supports Brooks) | S26: ='Outside Money'!D12
R27: Working Families Party PAC (supports Brooks) | S27: ='Outside Money'!D13
R28: Rural Freedom Network (supports Brooks) | S28: ='Outside Money'!D14
R29: Make the Road Action Political Committee (supports Brooks) | S29: ='Outside Money'!D15
R31: CHART 5: outside spending by target and stance
R32: Target and stance | S32: Amount
R33: Brooks, supports | S33: ='Outside Money'!C48
R34: Brooks, opposes | S34: ='Outside Money'!C49
R35: Mackenzie, supports | S35: ='Outside Money'!C50
R36: Mackenzie, opposes | S36: ='Outside Money'!C51
R38: CHART 6: concentration of outside spending
R39: Committee | S39: Outside spending
R40: Stronger Together PA | S40: ='Outside Money'!D6
R41: Hmp | S41: ='Outside Money'!D7
R42: Lead Left PAC | S42: ='Outside Money'!D8
R43: Jobs and Democracy PAC | S43: ='Outside Money'!D9
R44: Congressional Progressive Caucus PAC | S44: ='Outside Money'!D10
R45: Medicare for All | S45: ='Outside Money'!D11
R46: All other (32 committees) | S46: ='Outside Money'!D44-SUM('Outside Money'!D6:D11)
R48: CHART 7: spending by category
R49: Category | S49: Bob Brooks (D) | T49: Ryan Mackenzie (R)
R50: ='Spending Detail'!A6 | S50: ='Spending Detail'!B6 | T50: ='Spending Detail'!E6
R51: ='Spending Detail'!A7 | S51: ='Spending Detail'!B7 | T51: ='Spending Detail'!E7
R52: ='Spending Detail'!A8 | S52: ='Spending Detail'!B8 | T52: ='Spending Detail'!E8
R53: ='Spending Detail'!A9 | S53: ='Spending Detail'!B9 | T53: ='Spending Detail'!E9
R54: ='Spending Detail'!A10 | S54: ='Spending Detail'!B10 | T54: ='Spending Detail'!E10
R55: ='Spending Detail'!A11 | S55: ='Spending Detail'!B11 | T55: ='Spending Detail'!E11
R56: ='Spending Detail'!A12 | S56: ='Spending Detail'!B12 | T56: ='Spending Detail'!E12
R57: ='Spending Detail'!A13 | S57: ='Spending Detail'!B13 | T57: ='Spending Detail'!E13
R59: CHART 8: contributions by state
R60: State | S60: Bob Brooks (D) | T60: Ryan Mackenzie (R)
R61: ='Donor Detail'!A6 | S61: ='Donor Detail'!B6 | T61: ='Donor Detail'!E6
R62: ='Donor Detail'!A7 | S62: ='Donor Detail'!B7 | T62: ='Donor Detail'!E7
R63: ='Donor Detail'!A8 | S63: ='Donor Detail'!B8 | T63: ='Donor Detail'!E8
R64: ='Donor Detail'!A9 | S64: ='Donor Detail'!B9 | T64: ='Donor Detail'!E9
R65: ='Donor Detail'!A10 | S65: ='Donor Detail'!B10 | T65: ='Donor Detail'!E10
R66: ='Donor Detail'!A11 | S66: ='Donor Detail'!B11 | T66: ='Donor Detail'!E11
R67: ='Donor Detail'!A12 | S67: ='Donor Detail'!B12 | T67: ='Donor Detail'!E12
R68: ='Donor Detail'!A13 | S68: ='Donor Detail'!B13 | T68: ='Donor Detail'!E13
R70: CHART 9: what outside groups bought
R71: Category | S71: Outside spending
R72: ='Outside Detail'!A6 | S72: ='Outside Detail'!B6
R73: ='Outside Detail'!A7 | S73: ='Outside Detail'!B7
R74: ='Outside Detail'!A8 | S74: ='Outside Detail'!B8
R75: ='Outside Detail'!A9 | S75: ='Outside Detail'!B9
R76: ='Outside Detail'!A10 | S76: ='Outside Detail'!B10
R77: ='Outside Detail'!A11 | S77: ='Outside Detail'!B11
R78: ='Outside Detail'!A12 | S78: ='Outside Detail'!B12
R79: ='Outside Detail'!A13 | S79: ='Outside Detail'!B13
R80: ='Outside Detail'!A14 | S80: ='Outside Detail'!B14
R81: ='Outside Detail'!A15 | S81: ='Outside Detail'!B15

Sheet Money Sources
A1: Where each nominee's money came from
A2: Composition of receipts, and what changes when committee transfers are set aside.
A4: SOURCE OF FUNDS
A5: Source of funds | B5: Bob Brooks (D) | C5: Ryan Mackenzie (R) | D5: D, share of receipts | E5: R, share of receipts
A6: Individual, itemized (over $200) | B6: =IFERROR(IF(INDEX('Candidate Totals'!$K$6:$K$7,MATCH("Bob Brooks",'Candidate Totals'!$A$6:$A$7,0))=0,"",INDEX('Candidate Totals'!$K$6:$K$7,MATCH("Bob Brooks",'Candidate Totals'!$A$6:$A$7,0))-INDEX('Candidate Totals'!$L$6:$L$7,MATCH("Bob Brooks",'Candidate Totals'!$A$6:$A$7,0))),"") | C6: =IFERROR(IF(INDEX('Candidate Totals'!$K$6:$K$7,MATCH("Ryan Mackenzie",'Candidate Totals'!$A$6:$A$7,0))=0,"",INDEX('Candidate Totals'!$K$6:$K$7,MATCH("Ryan Mackenzie",'Candidate Totals'!$A$6:$A$7,0))-INDEX('Candidate Totals'!$L$6:$L$7,MATCH("Ryan Mackenzie",'Candidate Totals'!$A$6:$A$7,0))),"") | D6: =IF(AND(ISNUMBER(B6),ISNUMBER(B13)),B6/B13,"") | E6: =IF(AND(ISNUMBER(C6),ISNUMBER(C13)),C6/C13,"")
A7: Individual, unitemized ($200 or less) | B7: =IFERROR(IF(INDEX('Candidate Totals'!$L$6:$L$7,MATCH("Bob Brooks",'Candidate Totals'!$A$6:$A$7,0))=0,"",INDEX('Candidate Totals'!$L$6:$L$7,MATCH("Bob Brooks",'Candidate Totals'!$A$6:$A$7,0))),"") | C7: =IFERROR(IF(INDEX('Candidate Totals'!$L$6:$L$7,MATCH("Ryan Mackenzie",'Candidate Totals'!$A$6:$A$7,0))=0,"",INDEX('Candidate Totals'!$L$6:$L$7,MATCH("Ryan Mackenzie",'Candidate Totals'!$A$6:$A$7,0))),"") | D7: =IF(AND(ISNUMBER(B7),ISNUMBER(B13)),B7/B13,"") | E7: =IF(AND(ISNUMBER(C7),ISNUMBER(C13)),C7/C13,"")
A8: PAC contributions | B8: =IFERROR(IF(INDEX('Candidate Totals'!$M$6:$M$7,MATCH("Bob Brooks",'Candidate Totals'!$A$6:$A$7,0))=0,"",INDEX('Candidate Totals'!$M$6:$M$7,MATCH("Bob Brooks",'Candidate Totals'!$A$6:$A$7,0))),"") | C8: =IFERROR(IF(INDEX('Candidate Totals'!$M$6:$M$7,MATCH("Ryan Mackenzie",'Candidate Totals'!$A$6:$A$7,0))=0,"",INDEX('Candidate Totals'!$M$6:$M$7,MATCH("Ryan Mackenzie",'Candidate Totals'!$A$6:$A$7,0))),"") | D8: =IF(AND(ISNUMBER(B8),ISNUMBER(B13)),B8/B13,"") | E8: =IF(AND(ISNUMBER(C8),ISNUMBER(C13)),C8/C13,"")
A9: Party committee | B9: =IFERROR(IF(INDEX('Candidate Totals'!$N$6:$N$7,MATCH("Bob Brooks",'Candidate Totals'!$A$6:$A$7,0))=0,"",INDEX('Candidate Totals'!$N$6:$N$7,MATCH("Bob Brooks",'Candidate Totals'!$A$6:$A$7,0))),"") | C9: =IFERROR(IF(INDEX('Candidate Totals'!$N$6:$N$7,MATCH("Ryan Mackenzie",'Candidate Totals'!$A$6:$A$7,0))=0,"",INDEX('Candidate Totals'!$N$6:$N$7,MATCH("Ryan Mackenzie",'Candidate Totals'!$A$6:$A$7,0))),"") | D9: =IF(AND(ISNUMBER(B9),ISNUMBER(B13)),B9/B13,"") | E9: =IF(AND(ISNUMBER(C9),ISNUMBER(C13)),C9/C13,"")
A10: Transfers from another authorized committee | B10: =IFERROR(IF(INDEX('Candidate Totals'!$O$6:$O$7,MATCH("Bob Brooks",'Candidate Totals'!$A$6:$A$7,0))=0,"",INDEX('Candidate Totals'!$O$6:$O$7,MATCH("Bob Brooks",'Candidate Totals'!$A$6:$A$7,0))),"") | C10: =IFERROR(IF(INDEX('Candidate Totals'!$O$6:$O$7,MATCH("Ryan Mackenzie",'Candidate Totals'!$A$6:$A$7,0))=0,"",INDEX('Candidate Totals'!$O$6:$O$7,MATCH("Ryan Mackenzie",'Candidate Totals'!$A$6:$A$7,0))),"") | D10: =IF(AND(ISNUMBER(B10),ISNUMBER(B13)),B10/B13,"") | E10: =IF(AND(ISNUMBER(C10),ISNUMBER(C13)),C10/C13,"")
A11: Candidate self-funding | B11: =IFERROR(INDEX('Candidate Totals'!$P$6:$P$7,MATCH("Bob Brooks",'Candidate Totals'!$A$6:$A$7,0)),"") | C11: =IFERROR(INDEX('Candidate Totals'!$P$6:$P$7,MATCH("Ryan Mackenzie",'Candidate Totals'!$A$6:$A$7,0)),"") | D11: =IF(AND(ISNUMBER(B11),ISNUMBER(B13)),B11/B13,"") | E11: =IF(AND(ISNUMBER(C11),ISNUMBER(C13)),C11/C13,"")
A12: Other / unclassified | B12: =IFERROR(IF(INDEX('Candidate Totals'!$Q$6:$Q$7,MATCH("Bob Brooks",'Candidate Totals'!$A$6:$A$7,0))=0,"",INDEX('Candidate Totals'!$Q$6:$Q$7,MATCH("Bob Brooks",'Candidate Totals'!$A$6:$A$7,0))),"") | C12: =IFERROR(IF(INDEX('Candidate Totals'!$Q$6:$Q$7,MATCH("Ryan Mackenzie",'Candidate Totals'!$A$6:$A$7,0))=0,"",INDEX('Candidate Totals'!$Q$6:$Q$7,MATCH("Ryan Mackenzie",'Candidate Totals'!$A$6:$A$7,0))),"") | D12: =IF(AND(ISNUMBER(B12),ISNUMBER(B13)),B12/B13,"") | E12: =IF(AND(ISNUMBER(C12),ISNUMBER(C13)),C12/C13,"")
A13: TOTAL RECEIPTS | B13: =SUM(B6:B12) | C13: =SUM(C6:C12) | D13: =IFERROR(SUM(D6:D12),"") | E13: =IFERROR(SUM(E6:E12),"")
A14: Check: components minus reported receipts (must be $0) | B14: =IFERROR(B13-INDEX('Candidate Totals'!$G$6:$G$7,MATCH("Bob Brooks",'Candidate Totals'!$A$6:$A$7,0)),"") | C14: =IFERROR(C13-INDEX('Candidate Totals'!$G$6:$G$7,MATCH("Ryan Mackenzie",'Candidate Totals'!$A$6:$A$7,0)),"")
A16: THE HEADLINE GAP, AND WHAT IS IN IT
A17: Measure | B17: Bob Brooks (D) | C17: Ryan Mackenzie (R) | D17: R minus D
A18: Receipts as reported | B18: =IFERROR(IF(INDEX('Candidate Totals'!$G$6:$G$7,MATCH("Bob Brooks",'Candidate Totals'!$A$6:$A$7,0))=0,"",INDEX('Candidate Totals'!$G$6:$G$7,MATCH("Bob Brooks",'Candidate Totals'!$A$6:$A$7,0))),"") | C18: =IFERROR(IF(INDEX('Candidate Totals'!$G$6:$G$7,MATCH("Ryan Mackenzie",'Candidate Totals'!$A$6:$A$7,0))=0,"",INDEX('Candidate Totals'!$G$6:$G$7,MATCH("Ryan Mackenzie",'Candidate Totals'!$A$6:$A$7,0))),"") | D18: =IF(AND(ISNUMBER(C18),ISNUMBER(B18)),C18-B18,"")
A19: less: transfers from another authorized committee | B19: =IFERROR(IF(INDEX('Candidate Totals'!$O$6:$O$7,MATCH("Bob Brooks",'Candidate Totals'!$A$6:$A$7,0))=0,"",INDEX('Candidate Totals'!$O$6:$O$7,MATCH("Bob Brooks",'Candidate Totals'!$A$6:$A$7,0))),"") | C19: =IFERROR(IF(INDEX('Candidate Totals'!$O$6:$O$7,MATCH("Ryan Mackenzie",'Candidate Totals'!$A$6:$A$7,0))=0,"",INDEX('Candidate Totals'!$O$6:$O$7,MATCH("Ryan Mackenzie",'Candidate Totals'!$A$6:$A$7,0))),"") | D19: =IF(AND(ISNUMBER(C19),ISNUMBER(B19)),C19-B19,"")
A20: Receipts excluding committee transfers | B20: =IF(AND(ISNUMBER(B18),ISNUMBER(B19)),B18-B19,"") | C20: =IF(AND(ISNUMBER(C18),ISNUMBER(C19)),C18-C19,"") | D20: =IF(AND(ISNUMBER(C20),ISNUMBER(B20)),C20-B20,"")
A22: SMALL-DOLLAR SHARE
A23: Measure | B23: Bob Brooks (D) | C23: Ryan Mackenzie (R)
A24: Unitemized contributions ($200 or less) | B24: =IFERROR(IF(INDEX('Candidate Totals'!$L$6:$L$7,MATCH("Bob Brooks",'Candidate Totals'!$A$6:$A$7,0))=0,"",INDEX('Candidate Totals'!$L$6:$L$7,MATCH("Bob Brooks",'Candidate Totals'!$A$6:$A$7,0))),"") | C24: =IFERROR(IF(INDEX('Candidate Totals'!$L$6:$L$7,MATCH("Ryan Mackenzie",'Candidate Totals'!$A$6:$A$7,0))=0,"",INDEX('Candidate Totals'!$L$6:$L$7,MATCH("Ryan Mackenzie",'Candidate Totals'!$A$6:$A$7,0))),"")
A25: as a share of total receipts | B25: =IFERROR(B24/(INDEX('Candidate Totals'!$G$6:$G$7,MATCH("Bob Brooks",'Candidate Totals'!$A$6:$A$7,0))),"") | C25: =IFERROR(C24/(INDEX('Candidate Totals'!$G$6:$G$7,MATCH("Ryan Mackenzie",'Candidate Totals'!$A$6:$A$7,0))),"")
A26: as a share of individual contributions | B26: =IFERROR(B24/(INDEX('Candidate Totals'!$K$6:$K$7,MATCH("Bob Brooks",'Candidate Totals'!$A$6:$A$7,0))),"") | C26: =IFERROR(C24/(INDEX('Candidate Totals'!$K$6:$K$7,MATCH("Ryan Mackenzie",'Candidate Totals'!$A$6:$A$7,0))),"")
A28: SPENDING PACE AND CASH
A29: Measure | B29: Bob Brooks (D) | C29: Ryan Mackenzie (R) | D29: R minus D
A30: Receipts | B30: =IFERROR(IF(INDEX('Candidate Totals'!$G$6:$G$7,MATCH("Bob Brooks",'Candidate Totals'!$A$6:$A$7,0))=0,"",INDEX('Candidate Totals'!$G$6:$G$7,MATCH("Bob Brooks",'Candidate Totals'!$A$6:$A$7,0))),"") | C30: =IFERROR(IF(INDEX('Candidate Totals'!$G$6:$G$7,MATCH("Ryan Mackenzie",'Candidate Totals'!$A$6:$A$7,0))=0,"",INDEX('Candidate Totals'!$G$6:$G$7,MATCH("Ryan Mackenzie",'Candidate Totals'!$A$6:$A$7,0))),"") | D30: =IF(AND(ISNUMBER(C30),ISNUMBER(B30)),C30-B30,"")
A31: Disbursements | B31: =IFERROR(IF(INDEX('Candidate Totals'!$H$6:$H$7,MATCH("Bob Brooks",'Candidate Totals'!$A$6:$A$7,0))=0,"",INDEX('Candidate Totals'!$H$6:$H$7,MATCH("Bob Brooks",'Candidate Totals'!$A$6:$A$7,0))),"") | C31: =IFERROR(IF(INDEX('Candidate Totals'!$H$6:$H$7,MATCH("Ryan Mackenzie",'Candidate Totals'!$A$6:$A$7,0))=0,"",INDEX('Candidate Totals'!$H$6:$H$7,MATCH("Ryan Mackenzie",'Candidate Totals'!$A$6:$A$7,0))),"") | D31: =IF(AND(ISNUMBER(C31),ISNUMBER(B31)),C31-B31,"")
A32: Cash on hand | B32: =IFERROR(IF(INDEX('Candidate Totals'!$I$6:$I$7,MATCH("Bob Brooks",'Candidate Totals'!$A$6:$A$7,0))=0,"",INDEX('Candidate Totals'!$I$6:$I$7,MATCH("Bob Brooks",'Candidate Totals'!$A$6:$A$7,0))),"") | C32: =IFERROR(IF(INDEX('Candidate Totals'!$I$6:$I$7,MATCH("Ryan Mackenzie",'Candidate Totals'!$A$6:$A$7,0))=0,"",INDEX('Candidate Totals'!$I$6:$I$7,MATCH("Ryan Mackenzie",'Candidate Totals'!$A$6:$A$7,0))),"") | D32: =IF(AND(ISNUMBER(C32),ISNUMBER(B32)),C32-B32,"")
A33: Debts owed | B33: =IFERROR(INDEX('Candidate Totals'!$J$6:$J$7,MATCH("Bob Brooks",'Candidate Totals'!$A$6:$A$7,0)),"") | C33: =IFERROR(INDEX('Candidate Totals'!$J$6:$J$7,MATCH("Ryan Mackenzie",'Candidate Totals'!$A$6:$A$7,0)),"") | D33: =IF(AND(ISNUMBER(C33),ISNUMBER(B33)),C33-B33,"")
A34: Burn rate (disbursed / raised) | B34: =IF(AND(ISNUMBER(B31),ISNUMBER(B30),B30<>0),B31/B30,"") | C34: =IF(AND(ISNUMBER(C31),ISNUMBER(C30),C30<>0),C31/C30,"") | D34: =IF(AND(ISNUMBER(C34),ISNUMBER(B34)),C34-B34,"")
A35: Cash on hand / receipts | B35: =IF(AND(ISNUMBER(B32),ISNUMBER(B30),B30<>0),B32/B30,"") | C35: =IF(AND(ISNUMBER(C32),ISNUMBER(C30),C30<>0),C32/C30,"") | D35: =IF(AND(ISNUMBER(C35),ISNUMBER(B35)),C35-B35,"")
A37: Green figures link to Candidate Totals. Black figures are computed here. Debts are what the committee owes and are not netted out of cash on hand.

Sheet Candidate Totals
A1: Candidate committee totals, PA-07, 2026 cycle
A2: Cycle-to-date from each committee's latest periodic FEC report. Coverage through 2026-10-14. Retrieved 2026-10-24T13:15:11Z.
A4: THE TWO NOMINEES
A5: Candidate | B5: Party | C5: Status | D5: Incumbent | E5: Filed? | F5: Coverage through | G5: Receipts | H5: Disbursements | I5: Cash on hand | J5: Debts | K5: Individual, total | L5: of which unitemized ($200 or less) | M5: PAC contributions | N5: Party committee | O5: Transfers from other authorized committee | P5: Candidate self-funding | Q5: Other / unclassified (derived)
A6: Bob Brooks | B6: DEM | C6: Nominee | D6: no | E6: yes | F6: 2026-10-14 | G6: 5347353.4 | H6: 4605774.9 | I6: 741578.51 | J6: 15000 | K6: 4181508.3 | L6: 1167838.9 | M6: 634750.03 | N6: 6090.07 | O6: 508989.33 | P6: 3500 | Q6: =IF(ISNUMBER(G6),G6-(K6+M6+N6+O6+P6),"")
A7: Ryan Mackenzie | B7: REP | C7: Nominee | D7: yes | E7: yes | F7: 2026-10-14 | G7: 5296663.9 | H7: 4329911.2 | I7: 1069992.6 | J7: 1371.28 | K7: 1902194.1 | L7: 666386.88 | M7: 1314712.8 | N7: 10000 | O7: 2020364.9 | P7: 0 | Q7: =IF(ISNUMBER(G7),G7-(K7+M7+N7+O7+P7),"")
A8: TOTAL, both nominees | G8: =SUM(G6:G7) | H8: =SUM(H6:H7) | I8: =SUM(I6:I7) | J8: =SUM(J6:J7) | K8: =SUM(K6:K7) | L8: =SUM(L6:L7) | M8: =SUM(M6:M7) | N8: =SUM(N6:N7) | ... Q8: =SUM(Q6:Q7)
A10: HOW TO READ THIS TABLE
A11: This workbook covers the two general-election nominees named in sources/race.json. The FEC lists other declared and primary candidates for the seat; they stay in sources/fec.json and are not shown.
A12: A candidate with no periodic report on file would show BLANK financial cells, not $0. The FEC reports nothing in that case, which is a different claim from 'raised nothing'.
A13: 'of which unitemized' is a subset of 'Individual, total'. Adding it to the other source columns double-counts.
A14: Blue figures are values from the FEC API. Black figures are formulas.

Sheet Outside Money
A1: Outside spending (independent expenditures), PA-07, 2026
A2: Money spent by outside groups on their own to support or oppose one of the two nominees, without coordinating with the campaign. FEC's deduplicated by_candidate aggregate. Largest first. Spending about primary candidates not on the November ballot is not shown.
A4: BY COMMITTEE
A5: Committee | B5: Target candidate | C5: Stance | D5: Amount | E5: Filings | F5: Committee ID | G5: Share of all outside spending
A6: STRONGER TOGETHER PA | B6: Bob Brooks | C6: Supports | D6: 1781524 | E6: 21 | F6: C00936153 | G6: =IFERROR(D6/$D$44,"")
A7: HMP | B7: Ryan Mackenzie | C7: Opposes | D7: 556259.93 | E7: 11 | F7: C00495028 | G7: =IFERROR(D7/$D$44,"")
A8: LEAD LEFT PAC | B8: Bob Brooks | C8: Opposes | D8: 312371.76 | E8: 7 | F8: C00948208 | G8: =IFERROR(D8/$D$44,"")
A9: JOBS AND DEMOCRACY PAC | B9: Bob Brooks | C9: Supports | D9: 249750 | E9: 1 | F9: C00928374 | G9: =IFERROR(D9/$D$44,"")
A10: CONGRESSIONAL PROGRESSIVE CAUCUS PAC | B10: Bob Brooks | C10: Supports | D10: 140300 | E10: 2 | F10: C00513176 | G10: =IFERROR(D10/$D$44,"")
A11: MEDICARE FOR ALL | B11: Bob Brooks | C11: Supports | D11: 99625 | E11: 2 | F11: C00685552 | G11: =IFERROR(D11/$D$44,"")
A12: DLP PAC | B12: Bob Brooks | C12: Supports | D12: 88321.5 | E12: 4 | F12: C00895730 | G12: =IFERROR(D12/$D$44,"")
A13: WORKING FAMILIES PARTY PAC | B13: Bob Brooks | C13: Supports | D13: 41020.59 | E13: 3 | F13: C00606962 | G13: =IFERROR(D13/$D$44,"")
A14: RURAL FREEDOM NETWORK | B14: Bob Brooks | C14: Supports | D14: 30756.92 | E14: 5 | F14: C00647966 | G14: =IFERROR(D14/$D$44,"")
A15: MAKE THE ROAD ACTION POLITICAL COMMITTEE | B15: Bob Brooks | C15: Supports | D15: 30559.95 | E15: 9 | F15: C00689745 | G15: =IFERROR(D15/$D$44,"")
A16: HMP | B16: Bob Brooks | C16: Supports | D16: 30281.38 | E16: 4 | F16: C00495028 | G16: =IFERROR(D16/$D$44,"")
A17: IN UNION USA | B17: Ryan Mackenzie | C17: Opposes | D17: 26382.22 | E17: 1 | F17: C00745745 | G17: =IFERROR(D17/$D$44,"")
... A43: PENNSYLVANIA PRO-LIFE FEDERATION PAC | B43: Ryan Mackenzie | C43: Supports | D43: 22.94 | E43: 1 | F43: C00172361 | G43: =IFERROR(D43/$D$44,"")
A44: TOTAL | D44: =SUM(D6:D43) | G44: =IFERROR(SUM(G6:G43),"")
A46: BY TARGET CANDIDATE AND STANCE
A47: Target candidate | B47: Stance | C47: Amount | D47: Committees | E47: Share
A48: Bob Brooks | B48: Supports | C48: =SUMIFS($D$6:$D$43,$B$6:$B$43,A48,$C$6:$C$43,B48) | D48: =COUNTIFS($B$6:$B$43,A48,$C$6:$C$43,B48) | E48: =IFERROR(C48/$D$44,"")
A49: Bob Brooks | B49: Opposes | C49: =SUMIFS($D$6:$D$43,$B$6:$B$43,A49,$C$6:$C$43,B49) | D49: =COUNTIFS($B$6:$B$43,A49,$C$6:$C$43,B49) | E49: =IFERROR(C49/$D$44,"")
A50: Ryan Mackenzie | B50: Supports | C50: =SUMIFS($D$6:$D$43,$B$6:$B$43,A50,$C$6:$C$43,B50) | D50: =COUNTIFS($B$6:$B$43,A50,$C$6:$C$43,B50) | E50: =IFERROR(C50/$D$44,"")
A51: Ryan Mackenzie | B51: Opposes | C51: =SUMIFS($D$6:$D$43,$B$6:$B$43,A51,$C$6:$C$43,B51) | D51: =COUNTIFS($B$6:$B$43,A51,$C$6:$C$43,B51) | E51: =IFERROR(C51/$D$44,"")
A52: TOTAL | C52: =SUM(C48:C51) | D52: =SUM(D48:D51)
A54: HOW TO READ OUTSIDE SPENDING
A55: - Candidate totals are cycle-to-date from each committee's most recent periodic report (FEC Form 3). Independent expenditures report continuously and are usually fresher than the candidate totals; the two are not as of the same date.
A56: - Independent expenditures come from OpenFEC's schedules/schedule_e/by_candidate aggregate, FEC's own deduplication of amended and superseded filings. Summing raw itemized Schedule E lines instead would roughly double the figure and would be wrong.
A57: - That aggregate can lag a 24-hour notice by several weeks. Spending reported by notice in the last month may not yet appear here.
A58: - Candidates with no periodic report on file show blank fields, not $0. The FEC reports no figures for them, which is not the same as a confirmed zero.
A59: - 'PAC contributions' is FEC's other_political_committee_contributions: money given directly to the campaign by other political committees. It is a different thing from independent expenditures, which are spent by outside groups on their own and never pass through the campaign.
A60: - 'Self-funding' is FEC's candidate_contribution: the candidate's own money given or loaned to the campaign this cycle.

Sheet Spending Detail
A1: What each nominee's campaign spent its money on
A2: Itemized disbursements (each over $200), 2026 cycle, through 2026-10-14. Categories assigned from the description on each report. Retrieved 2026-10-23T15:04:41Z.
A4: SPENDING BY CATEGORY
A5: Category | B5: Bob Brooks (D) | C5: Share | D5: Items | E5: Ryan Mackenzie (R) | F5: Share | G5: Items
A6: Refunds | B6: 10375 | C6: =IF(AND(ISNUMBER(B6),ISNUMBER(B23),B23<>0),B6/B23,"") | D6: 12 | E6: 23204.28 | F6: =IF(AND(ISNUMBER(E6),ISNUMBER(E23),E23<>0),E6/E23,"") | G6: 65
A7: Fundraising | B7: 105581.67 | C7: =IF(AND(ISNUMBER(B7),ISNUMBER(B23),B23<>0),B7/B23,"") | D7: 169 | E7: 1017403.1 | F7: =IF(AND(ISNUMBER(E7),ISNUMBER(E23),E23<>0),E7/E23,"") | G7: 508
A8: Television advertising | B8: 521229 | C8: =IF(AND(ISNUMBER(B8),ISNUMBER(B23),B23<>0),B8/B23,"") | D8: 9 | E8: 0 | F8: =IF(AND(ISNUMBER(E8),ISNUMBER(E23),E23<>0),E8/E23,"") | G8: 0
A9: Digital advertising | B9: 258938.16 | C9: =IF(AND(ISNUMBER(B9),ISNUMBER(B23),B23<>0),B9/B23,"") | D9: 19 | E9: 2586 | F9: =IF(AND(ISNUMBER(E9),ISNUMBER(E23),E23<>0),E9/E23,"") | G9: 2
A10: Print and radio advertising | B10: 0 | C10: =IF(AND(ISNUMBER(B10),ISNUMBER(B23),B23<>0),B10/B23,"") | D10: 0 | E10: 3000 | F10: =IF(AND(ISNUMBER(E10),ISNUMBER(E23),E23<>0),E10/E23,"") | G10: 3
A11: Media production | B11: 34156.56 | C11: =IF(AND(ISNUMBER(B11),ISNUMBER(B23),B23<>0),B11/B23,"") | D11: 5 | E11: 11600 | F11: =IF(AND(ISNUMBER(E11),ISNUMBER(E23),E23<>0),E11/E23,"") | G11: 4
A12: Polling and research | B12: 41005 | C12: =IF(AND(ISNUMBER(B12),ISNUMBER(B23),B23<>0),B12/B23,"") | D12: 8 | E12: 41376.2 | F12: =IF(AND(ISNUMBER(E12),ISNUMBER(E23),E23<>0),E12/E23,"") | G12: 19
A13: Staff and payroll | B13: 204066.98 | C13: =IF(AND(ISNUMBER(B13),ISNUMBER(B23),B23<>0),B13/B23,"") | D13: 61 | E13: 3465 | F13: =IF(AND(ISNUMBER(E13),ISNUMBER(E23),E23<>0),E13/E23,"") | G13: 2
A14: Field, phones and texting | B14: 49977.25 | C14: =IF(AND(ISNUMBER(B14),ISNUMBER(B23),B23<>0),B14/B23,"") | D14: 16 | E14: 850 | F14: =IF(AND(ISNUMBER(E14),ISNUMBER(E23),E23<>0),E14/E23,"") | G14: 1
A15: Office and administrative | B15: 94451.94 | C15: =IF(AND(ISNUMBER(B15),ISNUMBER(B23),B23<>0),B15/B23,"") | D15: 48 | E15: 107158.6 | F15: =IF(AND(ISNUMBER(E15),ISNUMBER(E23),E23<>0),E15/E23,"") | G15: 252
A16: Mail and printing | B16: 22167.78 | C16: =IF(AND(ISNUMBER(B16),ISNUMBER(B23),B23<>0),B16/B23,"") | D16: 15 | E16: 36488.46 | F16: =IF(AND(ISNUMBER(E16),ISNUMBER(E23),E23<>0),E16/E23,"") | G16: 102
A17: Consulting | B17: 10000 | C17: =IF(AND(ISNUMBER(B17),ISNUMBER(B23),B23<>0),B17/B23,"") | D17: 1 | E17: 98693 | F17: =IF(AND(ISNUMBER(E17),ISNUMBER(E23),E23<>0),E17/E23,"") | G17: 51
A18: Signs and merchandise | B18: 750 | C18: =IF(AND(ISNUMBER(B18),ISNUMBER(B23),B23<>0),B18/B23,"") | D18: 1 | E18: 24202.36 | F18: =IF(AND(ISNUMBER(E18),ISNUMBER(E23),E23<>0),E18/E23,"") | G18: 12
A19: Travel | B19: 6186.67 | C19: =IF(AND(ISNUMBER(B19),ISNUMBER(B23),B23<>0),B19/B23,"") | D19: 20 | E19: 36958.81 | F19: =IF(AND(ISNUMBER(E19),ISNUMBER(E23),E23<>0),E19/E23,"") | G19: 91
A20: Events and meals | B20: 4117.43 | C20: =IF(AND(ISNUMBER(B20),ISNUMBER(B23),B23<>0),B20/B23,"") | D20: 12 | E20: 57849.89 | F20: =IF(AND(ISNUMBER(E20),ISNUMBER(E23),E23<>0),E20/E23,"") | G20: 140
A21: Contributions and donations | B21: 1333.76 | C21: =IF(AND(ISNUMBER(B21),ISNUMBER(B23),B23<>0),B21/B23,"") | D21: 6 | E21: 22575 | F21: =IF(AND(ISNUMBER(E21),ISNUMBER(E23),E23<>0),E21/E23,"") | G21: 9
A22: Other | B22: 4318.17 | C22: =IF(AND(ISNUMBER(B22),ISNUMBER(B23),B23<>0),B22/B23,"") | D22: 2 | E22: 0 | F22: =IF(AND(ISNUMBER(E22),ISNUMBER(E23),E23<>0),E22/E23,"") | G22: 0
A23: TOTAL itemized | B23: =SUM(B6:B22) | C23: =IF(AND(ISNUMBER(B23),ISNUMBER(B23),B23<>0),B23/B23,"") | D23: =SUM(D6:D22) | E23: =SUM(E6:E22) | F23: =IF(AND(ISNUMBER(E23),ISNUMBER(E23),E23<>0),E23/E23,"") | G23: =SUM(G6:G22)
A24: Check: categories minus FEC itemized total (must be $0) | B24: =B23-1368655.37 | E24: =E23-1487410.65
A26: LARGEST PAYEES, BOB BROOKS (D)
A27: Payee | B27: Amount | C27: Items | D27: City | E27: State | F27: Main category
A28: LC Media LLC | B28: 543229 | C28: 11 | D28: Huntingdon Valley | E28: PA | F28: Television advertising
A29: Ascend Digital | B29: 203646.79 | C29: 7 | D29: Washington | E29: DC | F29: Digital advertising
A30: Kaufman, Jenna | B30: 75187.4 | C30: 16 | D30: Bethlehem | E30: PA | F30: Staff and payroll
A31: Werner, Jack | B31: 58673.23 | C31: 17 | D31: Easton | E31: PA | F31: Staff and payroll
A32: Paychex | B32: 54920.71 | C32: 35 | D32: Rochester | E32: NY | F32: Staff and payroll
A33: Actblue Technical Services | B33: 54605.66 | C33: 76 | D33: West Somerville | E33: MA | F33: Fundraising
A34: Arc Initiatives | B34: 35000 | C34: 7 | D34: Washington | E34: DC | F34: Polling and research
A35: True Blue Digital | B35: 34817.13 | C35: 8 | D35: Chicago | E35: IL | F35: Digital advertising
A36: NGP VAN | B36: 31749.04 | C36: 5 | D36: Austin | E36: TX | F36: Office and administrative
A37: Cfo Compliance | B37: 26182.97 | C37: 9 | D37: Providence | E37: RI | F37: Office and administrative
A38: Wrigley, John | B38: 22312 | C38: 8 | D38: Allentown | E38: PA | F38: Staff and payroll
A39: Grassroots Analytics | B39: 17832.07 | C39: 12 | D39: Washington | E39: DC | F39: Fundraising
... A42: South Street Digital | B42: 14003.2 | C42: 3 | D42: Philadelphia | E42: PA | F42: Digital advertising
A44: LARGEST PAYEES, RYAN MACKENZIE (R)
A45: Payee | B45: Amount | C45: Items | D45: City | E45: State | F45: Main category
A46: Frontline Strategies | B46: 332817.9 | C46: 107 | D46: Elgin | E46: IL | F46: Fundraising
A47: District City Consulting | B47: 166301.16 | C47: 10 | D47: Washington | E47: DC | F47: Fundraising
A48: Christy Consulting LLC | B48: 132892.75 | C48: 27 | D48: Philadelphia | E48: PA | F48: Fundraising
A49: Fulfillment Solutions Inc. | B49: 74152.92 | C49: 31 | D49: Sterling | E49: VA | F49: Fundraising
A50: Direct Mail Fundraising LLC | B50: 64451.03 | C50: 16 | D50: Ashburn | E50: VA | F50: Fundraising
A51: Pathfinder Communications, LLC | B51: 52876.5 | C51: 15 | D51: Berwyn | E51: PA | F51: Consulting
A52: Weller, Andres | B52: 43138.83 | C52: 28 | D52: Emmaus | E52: PA | F52: Consulting
A53: Winred Technical Services, LLC | B53: 41412.94 | C53: 83 | D53: Cheyenne | E53: WY | F53: Fundraising
A54: Elite Consulting | B54: 40643.9 | C54: 10 | D54: Washington | E54: DC | F54: Fundraising
A55: The Tarrance Group | B55: 38124.5 | C55: 2 | D55: Alexandria | E55: VA | F55: Polling and research
A56: Rightway Compliance LLC | B56: 36592.58 | C56: 18 | D56: Harrisburg | E56: PA | F56: Office and administrative
A57: Managed By Equinox Inc | B57: 25875 | C57: 5 | D57: Bethlehem | E57: PA | F57: Office and administrative
... A60: Mackenzie, Ryan | B60: 20183.55 | C60: 36 | D60: Emmaus | E60: PA | F60: Travel
A62: WHERE THE PAYEES ARE
A63: Payee state | B63: Bob Brooks (D) | C63: Share | E63: Ryan Mackenzie (R) | F63: Share
A64: PA | B64: 798926.02 | C64: =IF(AND(ISNUMBER(B64),ISNUMBER(B23),B23<>0),B64/B23,"") | E64: 459357.16 | F64: =IF(AND(ISNUMBER(E64),ISNUMBER(E23),E23<>0),E64/E23,"")
A65: DC | B65: 274955.33 | C65: =IF(AND(ISNUMBER(B65),ISNUMBER(B23),B23<>0),B65/B23,"") | E65: 242504.01 | F65: =IF(AND(ISNUMBER(E65),ISNUMBER(E23),E23<>0),E65/E23,"")
A66: IL | B66: 35315.53 | C66: =IF(AND(ISNUMBER(B66),ISNUMBER(B23),B23<>0),B66/B23,"") | E66: 335283.52 | F66: =IF(AND(ISNUMBER(E66),ISNUMBER(E23),E23<>0),E66/E23,"")
A67: VA | B67: 1000 | C67: =IF(AND(ISNUMBER(B67),ISNUMBER(B23),B23<>0),B67/B23,"") | E67: 317942.8 | F67: =IF(AND(ISNUMBER(E67),ISNUMBER(E23),E23<>0),E67/E23,"")
A68: NY | B68: 69953.94 | C68: =IF(AND(ISNUMBER(B68),ISNUMBER(B23),B23<>0),B68/B23,"") | E68: 17435.36 | F68: =IF(AND(ISNUMBER(E68),ISNUMBER(E23),E23<>0),E68/E23,"")
A69: MA | B69: 57354.54 | C69: =IF(AND(ISNUMBER(B69),ISNUMBER(B23),B23<>0),B69/B23,"") | E69: 7613.56 | F69: =IF(AND(ISNUMBER(E69),ISNUMBER(E23),E23<>0),E69/E23,"")
A70: CA | B70: 39080.7 | C70: =IF(AND(ISNUMBER(B70),ISNUMBER(B23),B23<>0),B70/B23,"") | E70: 15050.7 | F70: =IF(AND(ISNUMBER(E70),ISNUMBER(E23),E23<>0),E70/E23,"")
A71: TX | B71: 32737.44 | C71: =IF(AND(ISNUMBER(B71),ISNUMBER(B23),B23<>0),B71/B23,"") | E71: 14439.86 | F71: =IF(AND(ISNUMBER(E71),ISNUMBER(E23),E23<>0),E71/E23,"")
A72: All other | B72: 59331.87 | C72: =IF(AND(ISNUMBER(B72),ISNUMBER(B23),B23<>0),B72/B23,"") | E72: 77783.68 | F72: =IF(AND(ISNUMBER(E72),ISNUMBER(E23),E23<>0),E72/E23,"")
A74: - Spending categories are assigned from the description each campaign wrote on its report, using ordered keyword rules (classify.py). The FEC's own purpose field files more than half of this spending as OTHER.
A75: - Memo sub-itemizations are excluded from spending, so the total equals FEC's by_purpose figure exactly.

Sheet Donor Detail
A1: Where each nominee's contributions came from
A2: Itemized individual contributions (each over $200), 2026 cycle, through 2026-10-14. FEC aggregates. Retrieved 2026-10-23T15:04:41Z.
A4: BY STATE
A5: State | B5: Bob Brooks (D) | C5: Share | D5: Gifts | E5: Ryan Mackenzie (R) | F5: Share | G5: Gifts
A6: PA | B6: 290329.06 | C6: =IF(AND(ISNUMBER(B6),ISNUMBER(B17),B17<>0),B6/B17,"") | D6: 687 | E6: 705177.53 | F6: =IF(AND(ISNUMBER(E6),ISNUMBER(E17),E17<>0),E6/E17,"") | G6: 1185
A7: FL | B7: 32808.59 | C7: =IF(AND(ISNUMBER(B7),ISNUMBER(B17),B17<>0),B7/B17,"") | D7: 42 | E7: 498858.16 | F7: =IF(AND(ISNUMBER(E7),ISNUMBER(E17),E17<>0),E7/E17,"") | G7: 1923
A8: NY | B8: 275445.73 | C8: =IF(AND(ISNUMBER(B8),ISNUMBER(B17),B17<>0),B8/B17,"") | D8: 206 | E8: 219095.46 | F8: =IF(AND(ISNUMBER(E8),ISNUMBER(E17),E17<>0),E8/E17,"") | G8: 420
A9: CA | B9: 232104.2 | C9: =IF(AND(ISNUMBER(B9),ISNUMBER(B17),B17<>0),B9/B17,"") | D9: 317 | E9: 189336.51 | F9: =IF(AND(ISNUMBER(E9),ISNUMBER(E17),E17<>0),E9/E17,"") | G9: 1371
A10: TX | B10: 16950 | C10: =IF(AND(ISNUMBER(B10),ISNUMBER(B17),B17<>0),B10/B17,"") | D10: 14 | E10: 392044.34 | F10: =IF(AND(ISNUMBER(E10),ISNUMBER(E17),E17<>0),E10/E17,"") | G10: 2187
A11: MA | B11: 162959.5 | C11: =IF(AND(ISNUMBER(B11),ISNUMBER(B17),B17<>0),B11/B17,"") | D11: 254 | E11: 53894.65 | F11: =IF(AND(ISNUMBER(E11),ISNUMBER(E17),E17<>0),E11/E17,"") | G11: 65
A12: IL | B12: 23197.32 | C12: =IF(AND(ISNUMBER(B12),ISNUMBER(B17),B17<>0),B12/B17,"") | D12: 43 | E12: 82720.37 | F12: =IF(AND(ISNUMBER(E12),ISNUMBER(E17),E17<>0),E12/E17,"") | G12: 404
A13: LA | B13: 0 | C13: =IF(AND(ISNUMBER(B13),ISNUMBER(B17),B17<>0),B13/B17,"") | D13: 0 | E13: 96564.66 | F13: =IF(AND(ISNUMBER(E13),ISNUMBER(E17),E17<>0),E13/E17,"") | G13: 230
A14: VA | B14: 14884.19 | C14: =IF(AND(ISNUMBER(B14),ISNUMBER(B17),B17<>0),B14/B17,"") | D14: 72 | E14: 80077.28 | F14: =IF(AND(ISNUMBER(E14),ISNUMBER(E17),E17<>0),E14/E17,"") | G14: 432
A15: CT | B15: 42688.16 | C15: =IF(AND(ISNUMBER(B15),ISNUMBER(B17),B17<>0),B15/B17,"") | D15: 41 | E15: 38941.97 | F15: =IF(AND(ISNUMBER(E15),ISNUMBER(E17),E17<>0),E15/E17,"") | G15: 98
A16: All other | B16: 270739.41 | C16: =IF(AND(ISNUMBER(B16),ISNUMBER(B17),B17<>0),B16/B17,"") | D16: 473 | E16: 587844.14 | F16: =IF(AND(ISNUMBER(E16),ISNUMBER(E17),E17<>0),E16/E17,"") | G16: 4931
A17: TOTAL itemized | B17: =SUM(B6:B16) | C17: =IF(AND(ISNUMBER(B17),ISNUMBER(B17),B17<>0),B17/B17,"") | D17: =SUM(D6:D16) | E17: =SUM(E6:E16) | F17: =IF(AND(ISNUMBER(E17),ISNUMBER(E17),E17<>0),E17/E17,"") | G17: =SUM(G6:G16)
A19: BY SIZE OF GIFT
A20: Size of gift | B20: Bob Brooks (D) | C20: Share | D20: Gifts | E20: Ryan Mackenzie (R) | F20: Share | G20: Gifts
A21: $200 or less | B21: 1213578.7 | C21: =IF(AND(ISNUMBER(B21),ISNUMBER(B26),B26<>0),B21/B26,"") | E21: 846543.27 | F21: =IF(AND(ISNUMBER(E21),ISNUMBER(E26),E26<>0),E21/E26,"")
A22: $200.01 to $499.99 | B22: 122396.32 | C22: =IF(AND(ISNUMBER(B22),ISNUMBER(B26),B26<>0),B22/B26,"") | D22: 453 | E22: 101351.85 | F22: =IF(AND(ISNUMBER(E22),ISNUMBER(E26),E26<>0),E22/E26,"") | G22: 372
A23: $500 to $999.99 | B23: 151953.87 | C23: =IF(AND(ISNUMBER(B23),ISNUMBER(B26),B26<>0),B23/B26,"") | D23: 292 | E23: 250771.82 | F23: =IF(AND(ISNUMBER(E23),ISNUMBER(E26),E26<>0),E23/E26,"") | G23: 443
A24: $1,000 to $1,999.99 | B24: 243422.46 | C24: =IF(AND(ISNUMBER(B24),ISNUMBER(B26),B26<>0),B24/B26,"") | D24: 224 | E24: 598054.96 | F24: =IF(AND(ISNUMBER(E24),ISNUMBER(E26),E26<>0),E24/E26,"") | G24: 482
A25: $2,000 and over | B25: 798593.73 | C25: =IF(AND(ISNUMBER(B25),ISNUMBER(B26),B26<>0),B25/B26,"") | D25: 246 | E25: 1814220.1 | F25: =IF(AND(ISNUMBER(E25),ISNUMBER(E26),E26<>0),E25/E26,"") | G25: 607
A26: TOTAL, all gifts | B26: =SUM(B21:B25) | C26: =IF(AND(ISNUMBER(B26),ISNUMBER(B26),B26<>0),B26/B26,"") | E26: =SUM(E21:E25) | F26: =IF(AND(ISNUMBER(E26),ISNUMBER(E26),E26<>0),E26/E26,"")
A27: Gifts of $200 or less are not itemized by donor, so their count is not reported. This table covers all receipts from individuals; the tables above and below cover itemized gifts only.
A29: IN THE DISTRICT
B30: Bob Brooks (D) | C30: Share | E30: Ryan Mackenzie (R) | F30: Share
A31: From zip codes 180xx, 181xx, 182xx, 183xx (Lehigh Valley and Poconos) | B31: 92671.33 | C31: =IF(AND(ISNUMBER(B31),ISNUMBER(B33),B33<>0),B31/B33,"") | E31: 395259.46 | F31: =IF(AND(ISNUMBER(E31),ISNUMBER(E33),E33<>0),E31/E33,"")
A32: From everywhere else | B32: =IF(AND(ISNUMBER(B31),ISNUMBER(B33)),B33-B31,"") | C32: =IF(AND(ISNUMBER(B32),ISNUMBER(B33),B33<>0),B32/B33,"") | E32: =IF(AND(ISNUMBER(E31),ISNUMBER(E33)),E33-E31,"") | F32: =IF(AND(ISNUMBER(E32),ISNUMBER(E33),E33<>0),E32/E33,"")
A33: TOTAL itemized, by zip | B33: 1362106.2 | C33: =IF(AND(ISNUMBER(B33),ISNUMBER(B33),B33<>0),B33/B33,"") | E33: 2944555.1 | F33: =IF(AND(ISNUMBER(E33),ISNUMBER(E33),E33<>0),E33/E33,"")
A34: Approximate. The FEC records no district for a donor; zip prefix is the closest available proxy and these prefixes reach slightly beyond the district line.
A36: TOP OCCUPATIONS, BOB BROOKS (D)
A37: Occupation, as reported by the donor | B37: Amount | C37: Gifts
A38: Not Employed | B38: 453408.96 | C38: 950
A39: Retired | B39: 112066.52 | C39: 121
A40: No Employer | B40: 98780.55 | C40: 118
A41: Attorney | B41: 58164.13 | C41: 77
A42: Ceo | B42: 44343.9 | C42: 21
A43: Physician | B43: 26135.41 | C43: 38
A44: Firefighter | B44: 25304 | C44: 86
A45: Consultant | B45: 25083.33 | C45: 53
A46: President | B46: 22300 | C46: 23
A47: Null | B47: 20900 | C47: 17
A49: TOP OCCUPATIONS, RYAN MACKENZIE (R)
A50: Occupation, as reported by the donor | B50: Amount | C50: Gifts
A51: Retired | B51: 757056.16 | C51: 10536
A52: Ceo | B52: 309337.13 | C52: 275
A53: Owner | B53: 169174.26 | C53: 142
A54: Chairman | B54: 126323.31 | C54: 75
A55: President | B55: 124651.54 | C55: 94
A56: Executive | B56: 107698.83 | C56: 71
A57: Founder | B57: 105830.87 | C57: 51
A58: Homemaker | B58: 76092.81 | C58: 49
A59: Investor | B59: 75497.97 | C59: 58
A60: Attorney | B60: 68701.13 | C60: 67
A62: Contribution figures are FEC aggregates of itemized contributions, those over $200. They include contributions routed through a joint fundraising committee, so a candidate whose receipts include a large transfer will show a by-state total above the committee's own individual-contribution line.

Sheet Outside Detail
A1: What each outside group bought
A2: Every itemized independent expenditure about one of the two nominees, 2026 cycle. Notices and memo entries removed; the total equals FEC's by_candidate aggregate for the nominees. Largest first.
A4: BY WHAT WAS BOUGHT
A5: Category | B5: Amount | C5: Share | D5: Items
A6: Digital advertising | B6: =SUMIFS($H$21:$H$158,$I$21:$I$158,A6) | C6: =IFERROR(B6/$H$159,"") | D6: =COUNTIFS($I$21:$I$158,A6)
A7: Radio | B7: =SUMIFS($H$21:$H$158,$I$21:$I$158,A7) | C7: =IFERROR(B7/$H$159,"") | D7: =COUNTIFS($I$21:$I$158,A7)
A8: Texting and phone calls | B8: =SUMIFS($H$21:$H$158,$I$21:$I$158,A8) | C8: =IFERROR(B8/$H$159,"") | D8: =COUNTIFS($I$21:$I$158,A8)
A9: Email | B9: =SUMIFS($H$21:$H$158,$I$21:$I$158,A9) | C9: =IFERROR(B9/$H$159,"") | D9: =COUNTIFS($I$21:$I$158,A9)
A10: Mail and print | B10: =SUMIFS($H$21:$H$158,$I$21:$I$158,A10) | C10: =IFERROR(B10/$H$159,"") | D10: =COUNTIFS($I$21:$I$158,A10)
A11: Canvassing and field | B11: =SUMIFS($H$21:$H$158,$I$21:$I$158,A11) | C11: =IFERROR(B11/$H$159,"") | D11: =COUNTIFS($I$21:$I$158,A11)
A12: Television and media buys | B12: =SUMIFS($H$21:$H$158,$I$21:$I$158,A12) | C12: =IFERROR(B12/$H$159,"") | D12: =COUNTIFS($I$21:$I$158,A12)
A13: Production | B13: =SUMIFS($H$21:$H$158,$I$21:$I$158,A13) | C13: =IFERROR(B13/$H$159,"") | D13: =COUNTIFS($I$21:$I$158,A13)
A14: Data | B14: =SUMIFS($H$21:$H$158,$I$21:$I$158,A14) | C14: =IFERROR(B14/$H$159,"") | D14: =COUNTIFS($I$21:$I$158,A14)
A15: Other | B15: =SUMIFS($H$21:$H$158,$I$21:$I$158,A15) | C15: =IFERROR(B15/$H$159,"") | D15: =COUNTIFS($I$21:$I$158,A15)
A16: TOTAL | B16: =SUM(B6:B15) | D16: =SUM(D6:D15)
A19: EVERY ITEMIZED EXPENDITURE
A20: Committee | B20: About | C20: Stance | D20: What was bought | E20: Paid to | F20: City | G20: State | H20: Amount | I20: Category | J20: Date
A21: Stronger Together PA | B21: Bob Brooks | C21: Supports | D21: Ad Buy | E21: Technicolor Campaigns, LLC | F21: Philadelphia | G21: PA | H21: 306418 | I21: Television and media buys | J21: 2026-05-05
A22: Stronger Together PA | B22: Bob Brooks | C22: Supports | D22: Ad Buy | E22: Technicolor Campaigns, LLC | F22: Philadelphia | G22: PA | H22: 272247 | I22: Television and media buys | J22: 2026-04-01
A23: Jobs and Democracy PAC | B23: Bob Brooks | C23: Supports | D23: Digital Buy | E23: Bryson Gillette, LLC | F23: Santa Barbara | G23: CA | H23: 249750 | I23: Digital advertising | J23: 2026-05-15
A24: Stronger Together PA | B24: Bob Brooks | C24: Supports | D24: Ad Buy | E24: Technicolor Campaigns, LLC | F24: Philadelphia | G24: PA | H24: 175000 | I24: Television and media buys | J24: 2026-05-13
A25: Stronger Together PA | B25: Bob Brooks | C25: Supports | D25: Ad Buy | E25: Technicolor Campaigns, LLC | F25: Philadelphia | G25: PA | H25: 154509 | I25: Television and media buys | J25: 2026-04-23
A26: Stronger Together PA | B26: Bob Brooks | C26: Supports | D26: Ad Buy | E26: Technicolor Campaigns, LLC | F26: Philadelphia | G26: PA | H26: 150000 | I26: Television and media buys | J26: 2026-05-15
A27: Hmp | B27: Ryan Mackenzie | C27: Opposes | D27: Digital Advertising | E27: Gambit Strategies LLC | F27: Washington | G27: DC | H27: 130875 | I27: Digital advertising | J27: 2026-09-25
A28: Hmp | B28: Ryan Mackenzie | C28: Opposes | D28: Digital Advertising | E28: Gambit Strategies LLC | F28: Washington | G28: DC | H28: 130875 | I28: Digital advertising | J28: 2026-09-23
A29: Congressional Progressive Caucus PAC | B29: Bob Brooks | C29: Supports | D29: Digital Ad Buy - Estimate | E29: Viewpoint Media LLC | F29: Berkeley | G29: CA | H29: 128000 | I29: Digital advertising | J29: 2026-04-24
A30: Hmp | B30: Ryan Mackenzie | C30: Opposes | D30: Digital Advertising | E30: Gambit Strategies LLC | F30: Washington | G30: DC | H30: 117732.94 | I30: Digital advertising | J30: 2026-09-14
A31: Stronger Together PA | B31: Bob Brooks | C31: Supports | D31: Ad Buy | E31: Technicolor Campaigns, LLC | F31: Philadelphia | G31: PA | H31: 110000 | I31: Television and media buys | J31: 2026-05-15
A32: Lead Left PAC | B32: Bob Brooks | C32: Opposes | D32: Media Placement / Media Production | E32: Otg Media LLC | F32: Richmond | G32: VA | H32: 106756.66 | I32: Television and media buys | J32: 2026-05-05
... A158: Givegreen United Action | B158: Bob Brooks | C158: Supports | D158: Text Messaging | E158: New Blue Interactive | F158: Bethesda | G158: MD | H158: 4.54 | I158: Texting and phone calls | J158: 2026-06-25
A159: TOTAL | H159: =SUM(H21:H158)
A160: Check: itemized total minus the by-candidate aggregate on Outside Money (must be $0) | H160: =H159-'Outside Money'!D44

Sheet History
A1: PA-07 general elections, 2018 to 2024: finance and results
A2: Final full-cycle FEC totals and certified vote totals. One row per nominee per election. Retrieved 2026-10-24T13:15:22Z.
A4: GENERAL-ELECTION NOMINEES
A5: Cycle | B5: Election date | C5: District map | D5: Candidate | E5: Party | F5: Incumbent | G5: Receipts | H5: Disbursements | I5: Cash on hand at year end | J5: Individual contributions | K5: PAC contributions | L5: Outside spending supporting | M5: Outside spending opposing | N5: Candidate plus aligned outside money | O5: General votes | P5: Two-party vote share | Q5: Result | R5: Receipts per vote | S5: Aligned money per vote
A6: 2018 | B6: 2018-11-06 | C6: 2018 PA Supreme Court remap (Lehigh Valley: Lehigh, Northampton, s. Monroe) | D6: Susan Wild | E6: DEM | F6: no | G6: 3320188 | H6: 3294280.3 | I6: 25907.69 | J6: 2216364.6 | K6: 535757.82 | L6: 558727.21 | M6: 221405.25 | N6: =IF(ISNUMBER(G6),G6+L6+SUMIFS($M$6:$M$13,$A$6:$A$13,$A6,$E$6:$E$13,"<>"&$E6),"") | O6: 140813 | P6: =IF(AND(ISNUMBER(O6),SUMIFS($O$6:$O$13,$A$6:$A$13,$A6)<>0),O6/SUMIFS($O$6:$O$13,$A$6:$A$13,$A6),"") | Q6: won | R6: =IF(AND(ISNUMBER(G6),ISNUMBER(O6),O6<>0),G6/O6,"") | S6: =IF(AND(ISNUMBER(N6),ISNUMBER(O6),O6<>0),N6/O6,"")
A7: 2018 | B7: 2018-11-06 | C7: 2018 PA Supreme Court remap (Lehigh Valley: Lehigh, Northampton, s. Monroe) | D7: Marty Nothstein | E7: REP | F7: no | G7: 985643.72 | H7: 958873.74 | I7: 26769.98 | J7: 611185.92 | K7: 223856.6 | L7: 132142.37 | M7: 1722119.9 | N7: =IF(ISNUMBER(G7),G7+L7+SUMIFS($M$6:$M$13,$A$6:$A$13,$A7,$E$6:$E$13,"<>"&$E7),"") | O7: 114437 | P7: =IF(AND(ISNUMBER(O7),SUMIFS($O$6:$O$13,$A$6:$A$13,$A7)<>0),O7/SUMIFS($O$6:$O$13,$A$6:$A$13,$A7),"") | Q7: lost | R7: =IF(AND(ISNUMBER(G7),ISNUMBER(O7),O7<>0),G7/O7,"") | S7: =IF(AND(ISNUMBER(N7),ISNUMBER(O7),O7<>0),N7/O7,"")
A8: 2020 | B8: 2020-11-03 | C8: 2018 PA Supreme Court remap (Lehigh Valley: Lehigh, Northampton, s. Monroe) | D8: Susan Wild | E8: DEM | F8: yes | G8: 4644289.9 | H8: 4591501.2 | I8: 78696.36 | J8: 3417373.9 | K8: 1027682 | L8: 50133.76 | M8: 127595.71 | N8: =IF(ISNUMBER(G8),G8+L8+SUMIFS($M$6:$M$13,$A$6:$A$13,$A8,$E$6:$E$13,"<>"&$E8),"") | O8: 195475 | P8: =IF(AND(ISNUMBER(O8),SUMIFS($O$6:$O$13,$A$6:$A$13,$A8)<>0),O8/SUMIFS($O$6:$O$13,$A$6:$A$13,$A8),"") | Q8: won | R8: =IF(AND(ISNUMBER(G8),ISNUMBER(O8),O8<>0),G8/O8,"") | S8: =IF(AND(ISNUMBER(N8),ISNUMBER(O8),O8<>0),N8/O8,"")
A9: 2020 | B9: 2020-11-03 | C9: 2018 PA Supreme Court remap (Lehigh Valley: Lehigh, Northampton, s. Monroe) | D9: Lisa Scheller | E9: REP | F9: no | G9: 3740779 | H9: 3661738.3 | I9: 79040.75 | J9: 998798.19 | K9: 231174.7 | L9: 600145.56 | M9: 1165.62 | N9: =IF(ISNUMBER(G9),G9+L9+SUMIFS($M$6:$M$13,$A$6:$A$13,$A9,$E$6:$E$13,"<>"&$E9),"") | O9: 181407 | P9: =IF(AND(ISNUMBER(O9),SUMIFS($O$6:$O$13,$A$6:$A$13,$A9)<>0),O9/SUMIFS($O$6:$O$13,$A$6:$A$13,$A9),"") | Q9: lost | R9: =IF(AND(ISNUMBER(G9),ISNUMBER(O9),O9<>0),G9/O9,"") | S9: =IF(AND(ISNUMBER(N9),ISNUMBER(O9),O9<>0),N9/O9,"")
A10: 2022 | B10: 2022-11-08 | C10: 2022 post-census remap (Lehigh, Northampton, Carbon, part of Monroe) | D10: Susan Wild | E10: DEM | F10: yes | G10: 7002291.2 | H10: 7027026.2 | I10: 53961.35 | J10: 5366116.2 | K10: 1279735.8 | L10: 655273.84 | M10: 10853652 | N10: =IF(ISNUMBER(G10),G10+L10+SUMIFS($M$6:$M$13,$A$6:$A$13,$A10,$E$6:$E$13,"<>"&$E10),"") | O10: 151364 | P10: =IF(AND(ISNUMBER(O10),SUMIFS($O$6:$O$13,$A$6:$A$13,$A10)<>0),O10/SUMIFS($O$6:$O$13,$A$6:$A$13,$A10),"") | Q10: won | R10: =IF(AND(ISNUMBER(G10),ISNUMBER(O10),O10<>0),G10/O10,"") | S10: =IF(AND(ISNUMBER(N10),ISNUMBER(O10),O10<>0),N10/O10,"")
A11: 2022 | B11: 2022-11-08 | C11: 2022 post-census remap (Lehigh, Northampton, Carbon, part of Monroe) | D11: Lisa Scheller | E11: REP | F11: no | G11: 6354578.7 | H11: 6432421.6 | I11: 2737.49 | J11: 2381481.3 | K11: 514762 | L11: 23268.88 | M11: 8764085.8 | N11: =IF(ISNUMBER(G11),G11+L11+SUMIFS($M$6:$M$13,$A$6:$A$13,$A11,$E$6:$E$13,"<>"&$E11),"") | O11: 145527 | P11: =IF(AND(ISNUMBER(O11),SUMIFS($O$6:$O$13,$A$6:$A$13,$A11)<>0),O11/SUMIFS($O$6:$O$13,$A$6:$A$13,$A11),"") | Q11: lost | R11: =IF(AND(ISNUMBER(G11),ISNUMBER(O11),O11<>0),G11/O11,"") | S11: =IF(AND(ISNUMBER(N11),ISNUMBER(O11),O11<>0),N11/O11,"")
A12: 2024 | B12: 2024-11-05 | C12: 2022 post-census remap (Lehigh, Northampton, Carbon, part of Monroe) | D12: Susan Wild | E12: DEM | F12: yes | G12: 8960927.7 | H12: 8946230 | I12: 68659 | J12: 6604896.4 | K12: 1393265.5 | L12: 4568368.8 | M12: 10424863 | N12: =IF(ISNUMBER(G12),G12+L12+SUMIFS($M$6:$M$13,$A$6:$A$13,$A12,$E$6:$E$13,"<>"&$E12),"") | O12: 199626 | P12: =IF(AND(ISNUMBER(O12),SUMIFS($O$6:$O$13,$A$6:$A$13,$A12)<>0),O12/SUMIFS($O$6:$O$13,$A$6:$A$13,$A12),"") | Q12: lost | R12: =IF(AND(ISNUMBER(G12),ISNUMBER(O12),O12<>0),G12/O12,"") | S12: =IF(AND(ISNUMBER(N12),ISNUMBER(O12),O12<>0),N12/O12,"")
A13: 2024 | B13: 2024-11-05 | C13: 2022 post-census remap (Lehigh, Northampton, Carbon, part of Monroe) | D13: Ryan Mackenzie | E13: REP | F13: no | G13: 1818407.1 | H13: 1715167.2 | I13: 103239.91 | J13: 886645.14 | K13: 419249.05 | L13: 1333061.8 | M13: 9962854.1 | N13: =IF(ISNUMBER(G13),G13+L13+SUMIFS($M$6:$M$13,$A$6:$A$13,$A13,$E$6:$E$13,"<>"&$E13),"") | O13: 203688 | P13: =IF(AND(ISNUMBER(O13),SUMIFS($O$6:$O$13,$A$6:$A$13,$A13)<>0),O13/SUMIFS($O$6:$O$13,$A$6:$A$13,$A13),"") | Q13: won | R13: =IF(AND(ISNUMBER(G13),ISNUMBER(O13),O13<>0),G13/O13,"") | S13: =IF(AND(ISNUMBER(N13),ISNUMBER(O13),O13<>0),N13/O13,"")
A15: TOTAL VOTES CAST, AND WHAT TWO-PARTY SHARE LEAVES OUT
A16: Cycle | O16: Total votes cast | P16: Third-party and write-in | Q16: Third-party share | R16: Reconciliation
A17: 2018 | D17: All candidates on the ballot | O17: 263360 | P17: 8110 | Q17: =IF(AND(ISNUMBER(O17),ISNUMBER(P17),O17<>0),P17/O17,"") | R17: =IF(NOT(ISNUMBER(O17)),"not reported",IF(ABS(SUMIF($A$6:$A$13,$A17,$O$6:$O$13)+IF(ISNUMBER(P17),P17,0)-O17)<0.5,"ok","MISMATCH"))
A18: 2020 | D18: All candidates on the ballot | O18: 377404 | P18: 522 | Q18: =IF(AND(ISNUMBER(O18),ISNUMBER(P18),O18<>0),P18/O18,"") | R18: =IF(NOT(ISNUMBER(O18)),"not reported",IF(ABS(SUMIF($A$6:$A$13,$A18,$O$6:$O$13)+IF(ISNUMBER(P18),P18,0)-O18)<0.5,"ok","MISMATCH"))
A19: 2022 | D19: All candidates on the ballot | O19: 297395 | P19: 504 | Q19: =IF(AND(ISNUMBER(O19),ISNUMBER(P19),O19<>0),P19/O19,"") | R19: =IF(NOT(ISNUMBER(O19)),"not reported",IF(ABS(SUMIF($A$6:$A$13,$A19,$O$6:$O$13)+IF(ISNUMBER(P19),P19,0)-O19)<0.5,"ok","MISMATCH"))
A20: 2024 | D20: All candidates on the ballot | Q20: =IF(AND(ISNUMBER(O20),ISNUMBER(P20),O20<>0),P20/O20,"") | R20: =IF(NOT(ISNUMBER(O20)),"not reported",IF(ABS(SUMIF($A$6:$A$13,$A20,$O$6:$O$13)+IF(ISNUMBER(P20),P20,0)-O20)<0.5,"ok","MISMATCH"))
D21: Check: two-party plus third-party equals total, for every cycle that reports a total | R21: =COUNTIF(R17:R20,"MISMATCH")
A23: HOW TO READ THIS SHEET
A24: - DISTRICT BOUNDARIES CHANGED INSIDE THIS WINDOW. 2018 and 2020 were run on the 2018 PA Supreme Court remap; 2022 and 2024 on the post-2020-census remap, which added Carbon County and changed the Monroe County portion. The seat is Lehigh Valley-based throughout, so the four elections are broadly comparable, but they are not the identical electorate.
A25: - Susan Wild's FEC candidate record is filed under district 15 for cycle 2018 (candidate_id H8PA15195-era numbering, H8PA15229), because she first filed in the pre-remap PA-15. A query of /elections/?district=07&cycle=2018 therefore OMITS her entirely. Her totals here were pulled directly by candidate_id.
A26: - In 2018 Wild simultaneously contested the FULL TERM in the new PA-07 and the UNEXPIRED TERM special election in the old PA-15 (both on 2018-11-06). Her single committee funded both, so her 2018 receipts are not a clean 'PA-07 general election' figure. The vote total used here is the FULL TERM (new PA-07) race.
A27: - 'Other votes' are third-party and scattered write-in votes reported in the official results. 2018 included a Libertarian (Tim Silfies) who took 3.0% of the vote; the other three cycles were effectively two-candidate races.
A28: - Two-party vote share (used for the correlation and regression) is a candidate's votes divided by the sum of the Democratic and Republican votes only. This is the standard comparable measure when third-party presence varies across years, as it does here.
A29: - The Clerk of the House summary for 2024 lists only the two major-party nominees and reports no all-candidate district total. Third-party and write-in votes for 2024 are therefore unknown and recorded as null, not zero.
A30: - Finance figures are full-cycle totals through 31 December of the election year and are final, unlike the current-cycle figures, which are mid-cycle.
A31: - In 2018 Susan Wild's single committee financed two concurrent races (the PA-07 full term and the PA-15 unexpired term), so her 2018 receipts are not a clean PA-07 figure. The vote total used is the full-term race.

Sheet History Charts
A1: Money and results, 2018 to 2024
A2: Every series links to the History and Money vs Results sheets. Source data in columns R onward. | R2: CHART 1: all aligned money by cycle
R3: Cycle | S3: Democratic side | T3: Republican side
R4: 2018 | S4: ='Money vs Results'!E6 | T4: ='Money vs Results'!F6
R5: 2020 | S5: ='Money vs Results'!E7 | T5: ='Money vs Results'!F7
R6: 2022 | S6: ='Money vs Results'!E8 | T6: ='Money vs Results'!F8
R7: 2024 | S7: ='Money vs Results'!E9 | T7: ='Money vs Results'!F9
R9: CHART 2: candidate receipts by cycle
R10: Cycle | S10: Democratic nominee | T10: Republican nominee
R11: 2018 | S11: ='Money vs Results'!B6 | T11: ='Money vs Results'!C6
R12: 2020 | S12: ='Money vs Results'!B7 | T12: ='Money vs Results'!C7
R13: 2022 | S13: ='Money vs Results'!B8 | T13: ='Money vs Results'!C8
R14: 2024 | S14: ='Money vs Results'!B9 | T14: ='Money vs Results'!C9
R16: CHART 3: aligned money share vs vote share (Model B)
R17: Cycle | S17: D share of all aligned money | T17: D two-party vote share
R18: 2018 | S18: ='Money vs Results'!G6 | T18: ='Money vs Results'!H6
R19: 2020 | S19: ='Money vs Results'!G7 | T19: ='Money vs Results'!H7
R20: 2022 | S20: ='Money vs Results'!G8 | T20: ='Money vs Results'!H8
R21: 2024 | S21: ='Money vs Results'!G9 | T21: ='Money vs Results'!H9
R23: CHART 4: receipts share vs vote share (Model A)
R24: Cycle | S24: D share of candidate receipts | T24: D two-party vote share
R25: 2018 | S25: ='Money vs Results'!D6 | T25: ='Money vs Results'!H6
R26: 2020 | S26: ='Money vs Results'!D7 | T26: ='Money vs Results'!H7
R27: 2022 | S27: ='Money vs Results'!D8 | T27: ='Money vs Results'!H8
R28: 2024 | S28: ='Money vs Results'!D9 | T28: ='Money vs Results'!H9
R30: CHART 5: Democratic two-party vote share
R31: Cycle | S31: D two-party vote share | T31: 50%
R32: 2018 | S32: ='Money vs Results'!H6 | T32: 0.5
R33: 2020 | S33: ='Money vs Results'!H7 | T33: 0.5
R34: 2022 | S34: ='Money vs Results'!H8 | T34: 0.5
R35: 2024 | S35: ='Money vs Results'!H9 | T35: 0.5
R37: CHART 6: candidate money vs outside money
R38: Cycle | S38: Candidate committees | T38: Outside spending
R39: 2018 | S39: ='Money vs Results'!B6+'Money vs Results'!C6 | T39: =('Money vs Results'!E6+'Money vs Results'!F6)-('Money vs Results'!B6+'Money vs Results'!C6)
R40: 2020 | S40: ='Money vs Results'!B7+'Money vs Results'!C7 | T40: =('Money vs Results'!E7+'Money vs Results'!F7)-('Money vs Results'!B7+'Money vs Results'!C7)
R41: 2022 | S41: ='Money vs Results'!B8+'Money vs Results'!C8 | T41: =('Money vs Results'!E8+'Money vs Results'!F8)-('Money vs Results'!B8+'Money vs Results'!C8)
R42: 2024 | S42: ='Money vs Results'!B9+'Money vs Results'!C9 | T42: =('Money vs Results'!E9+'Money vs Results'!F9)-('Money vs Results'!B9+'Money vs Results'!C9)
R44: CHART 7: receipts per vote received
R45: Candidate | S45: Receipts per vote
R46: 2018 Wild (D) | S46: =History!R6
R47: 2018 Nothstein (R) | S47: =History!R7
R48: 2020 Wild (D) | S48: =History!R8
R49: 2020 Scheller (R) | S49: =History!R9
R50: 2022 Wild (D) | S50: =History!R10
R51: 2022 Scheller (R) | S51: =History!R11
R52: 2024 Wild (D) | S52: =History!R12
R53: 2024 Mackenzie (R) | S53: =History!R13

Sheet Money vs Results
A1: Does money predict the result in PA-07?
A2: Four elections. The Democratic side's share of money against its share of the two-party vote. Links to the History sheet.
A4: CYCLE SUMMARY
A5: Election cycle | B5: D candidate receipts | C5: R candidate receipts | D5: D share of candidate receipts | E5: D side, candidate plus aligned outside | F5: R side, candidate plus aligned outside | G5: D share of all aligned money | H5: D two-party vote share
A6: 2018 | B6: =SUMIFS(History!$G$6:$G$13,History!$A$6:$A$13,$A6,History!$E$6:$E$13,"DEM") | C6: =SUMIFS(History!$G$6:$G$13,History!$A$6:$A$13,$A6,History!$E$6:$E$13,"REP") | D6: =IF(B6+C6=0,"",B6/(B6+C6)) | E6: =SUMIFS(History!$N$6:$N$13,History!$A$6:$A$13,$A6,History!$E$6:$E$13,"DEM") | F6: =SUMIFS(History!$N$6:$N$13,History!$A$6:$A$13,$A6,History!$E$6:$E$13,"REP") | G6: =IF(E6+F6=0,"",E6/(E6+F6)) | H6: =SUMIFS(History!$P$6:$P$13,History!$A$6:$A$13,$A6,History!$E$6:$E$13,"DEM")
A7: 2020 | B7: =SUMIFS(History!$G$6:$G$13,History!$A$6:$A$13,$A7,History!$E$6:$E$13,"DEM") | C7: =SUMIFS(History!$G$6:$G$13,History!$A$6:$A$13,$A7,History!$E$6:$E$13,"REP") | D7: =IF(B7+C7=0,"",B7/(B7+C7)) | E7: =SUMIFS(History!$N$6:$N$13,History!$A$6:$A$13,$A7,History!$E$6:$E$13,"DEM") | F7: =SUMIFS(History!$N$6:$N$13,History!$A$6:$A$13,$A7,History!$E$6:$E$13,"REP") | G7: =IF(E7+F7=0,"",E7/(E7+F7)) | H7: =SUMIFS(History!$P$6:$P$13,History!$A$6:$A$13,$A7,History!$E$6:$E$13,"DEM")
A8: 2022 | B8: =SUMIFS(History!$G$6:$G$13,History!$A$6:$A$13,$A8,History!$E$6:$E$13,"DEM") | C8: =SUMIFS(History!$G$6:$G$13,History!$A$6:$A$13,$A8,History!$E$6:$E$13,"REP") | D8: =IF(B8+C8=0,"",B8/(B8+C8)) | E8: =SUMIFS(History!$N$6:$N$13,History!$A$6:$A$13,$A8,History!$E$6:$E$13,"DEM") | F8: =SUMIFS(History!$N$6:$N$13,History!$A$6:$A$13,$A8,History!$E$6:$E$13,"REP") | G8: =IF(E8+F8=0,"",E8/(E8+F8)) | H8: =SUMIFS(History!$P$6:$P$13,History!$A$6:$A$13,$A8,History!$E$6:$E$13,"DEM")
A9: 2024 | B9: =SUMIFS(History!$G$6:$G$13,History!$A$6:$A$13,$A9,History!$E$6:$E$13,"DEM") | C9: =SUMIFS(History!$G$6:$G$13,History!$A$6:$A$13,$A9,History!$E$6:$E$13,"REP") | D9: =IF(B9+C9=0,"",B9/(B9+C9)) | E9: =SUMIFS(History!$N$6:$N$13,History!$A$6:$A$13,$A9,History!$E$6:$E$13,"DEM") | F9: =SUMIFS(History!$N$6:$N$13,History!$A$6:$A$13,$A9,History!$E$6:$E$13,"REP") | G9: =IF(E9+F9=0,"",E9/(E9+F9)) | H9: =SUMIFS(History!$P$6:$P$13,History!$A$6:$A$13,$A9,History!$E$6:$E$13,"DEM")
A11: CORRELATION AND LINEAR REGRESSION
A12: Statistic | B12: Model A: candidate receipts only | C12: Model B: candidate plus outside money
A13: Observations (n) | B13: =COUNT(H6:H9) | C13: =COUNT(H6:H9)
A14: Pearson correlation r | B14: =IFERROR(CORREL(D6:D9,H6:H9),"") | C14: =IFERROR(CORREL(G6:G9,H6:H9),"")
A15: R squared (variance explained) | B15: =IFERROR(RSQ(H6:H9,D6:D9),"") | C15: =IFERROR(RSQ(H6:H9,G6:G9),"")
A16: Slope (change in vote share per 1.0 of money share) | B16: =IFERROR(SLOPE(H6:H9,D6:D9),"") | C16: =IFERROR(SLOPE(H6:H9,G6:G9),"")
A17: Intercept | B17: =IFERROR(INTERCEPT(H6:H9,D6:D9),"") | C17: =IFERROR(INTERCEPT(H6:H9,G6:G9),"")
A18: Standard error of the slope | B18: =IFERROR(STEYX(H6:H9,D6:D9)/SQRT(DEVSQ(D6:D9)),"") | C18: =IFERROR(STEYX(H6:H9,G6:G9)/SQRT(DEVSQ(G6:G9)),"")
A19: t-statistic for the slope | B19: =IF(AND(ISNUMBER(B16),ISNUMBER(B18),B18<>0),B16/B18,"") | C19: =IF(AND(ISNUMBER(C16),ISNUMBER(C18),C18<>0),C16/C18,"")
A20: p-value (two-tailed) | B20: =IF(AND(ISNUMBER(B19),B21>0),IFERROR(TDIST(ABS(B19),B21,2),""),"") | C20: =IF(AND(ISNUMBER(C19),C21>0),IFERROR(TDIST(ABS(C19),C21,2),""),"")
A21: Degrees of freedom | B21: =IF(ISNUMBER(B13),B13-2,"") | C21: =IF(ISNUMBER(C13),C13-2,"")
A22: Statistically significant at p < 0.05? | B22: =IF(ISNUMBER(B20),IF(B20<0.05,"yes","no: cannot reject the null"),"") | C22: =IF(ISNUMBER(C20),IF(C20<0.05,"yes","no: cannot reject the null"),"")
A24: MODEL B: FITTED VALUES AND RESIDUALS
A25: Election cycle | B25: Actual D two-party vote share | C25: Predicted by Model B | D25: Residual (actual minus predicted) | E25: D share of all aligned money
A26: =A6 | B26: =H6 | C26: =IF(AND(ISNUMBER($C$17),ISNUMBER($C$16),ISNUMBER(E26)),$C$17+$C$16*E26,"") | D26: =IF(AND(ISNUMBER(B26),ISNUMBER(C26)),B26-C26,"") | E26: =G6
A27: =A7 | B27: =H7 | C27: =IF(AND(ISNUMBER($C$17),ISNUMBER($C$16),ISNUMBER(E27)),$C$17+$C$16*E27,"") | D27: =IF(AND(ISNUMBER(B27),ISNUMBER(C27)),B27-C27,"") | E27: =G7
A28: =A8 | B28: =H8 | C28: =IF(AND(ISNUMBER($C$17),ISNUMBER($C$16),ISNUMBER(E28)),$C$17+$C$16*E28,"") | D28: =IF(AND(ISNUMBER(B28),ISNUMBER(C28)),B28-C28,"") | E28: =G8
A29: =A9 | B29: =H9 | C29: =IF(AND(ISNUMBER($C$17),ISNUMBER($C$16),ISNUMBER(E29)),$C$17+$C$16*E29,"") | D29: =IF(AND(ISNUMBER(B29),ISNUMBER(C29)),B29-C29,"") | E29: =G9
A31: WHAT THIS DOES AND DOES NOT ESTABLISH
A32: n = 4. This cannot support a statistical claim. With four elections and two fitted parameters there are two degrees of freedom, and the confidence interval on the slope is wider than any effect it could detect. The regression is reported because it was asked for and because it disciplines the description, not because it licenses an inference. Treat every figure above as descriptive.
A33: Model A is the one that matters, and it finds nothing. The Democratic share of candidate fundraising has essentially no relationship to the Democratic share of the vote in this district (R squared near zero). 2024 is decisive on its own: Susan Wild raised 83% of all candidate money in the race and lost it.
A34: Model B does better because it counts the outside money. Once independent expenditures are added, including money spent attacking the opponent, the relationship turns positive. It is still not significant at n = 4, and the ordering is dominated by 2018, a Democratic wave year in which the Republican was barely funded.
A35: The causation runs both ways, and mostly backwards. Money flows toward races already expected to be close, and toward candidates already expected to win. A positive correlation is as consistent with 'donors can spot a winner' as with 'spending buys votes'. Nothing here separates the two.
A36: The omitted variable is the national environment. 2018 was a Democratic wave; 2024 was a Republican-leaning presidential year in a district trending right. Those two facts explain the vote-share series better than money does, and they are not in the model.

Sheet Notes & Sources
A1: Notes, sources and known limitations
A3: SOURCES
A4: Current cycle: FEC / OpenFEC API, https://www.fec.gov/data/elections/house/PA/07/2026/, retrieved 2026-10-24T13:15:11Z
A5: History, finance: OpenFEC API (finance); certified results from sources/results.json, retrieved 2026-10-24T13:15:22Z
A6: History, 2018 results: FEC, Federal Elections 2018, '2018 US House Results by State', district '07 - FULL TERM' (https://www.fec.gov/documents/2706/federalelections2018.xlsx)
A7: History, 2020 results: FEC, Federal Elections 2020, '13. US House Results by State', district '07' (https://www.fec.gov/documents/4228/federalelections2020.xlsx)
A8: History, 2022 results: FEC, Federal Elections 2022, '8. US House Results by State', district '07' (https://www.fec.gov/documents/5676/federalelections2022.xlsx)
A9: History, 2024 results: Clerk of the U.S. House, Statistics of the Congressional Election of November 5, 2024, p.61 (Pennsylvania, district 7) (https://clerk.house.gov/member_info/electionInfo/2024/statistics2024.pdf)
A11: NOTES
A12: - Candidate totals are cycle-to-date from each committee's most recent periodic report (FEC Form 3). Independent expenditures report continuously and are usually fresher than the candidate totals; the two are not as of the same date.
A13: - Independent expenditures come from OpenFEC's schedules/schedule_e/by_candidate aggregate, FEC's own deduplication of amended and superseded filings. Summing raw itemized Schedule E lines instead would roughly double the figure and would be wrong.
A14: - That aggregate can lag a 24-hour notice by several weeks. Spending reported by notice in the last month may not yet appear here.
... A37: - This workbook is rebuilt from sources/ on every scheduled run of the pa07-finance repository.
